Workbook

Sheet README
A1: Nyaymalaw - Build Plan
A2: Generated 2026-08-27 from docs/PRD.md and docs/ARCHITECTURE.md
A5: What this is | B5: The full build to an enterprise-grade NM. Sheets: Backlog (the work), Epics (grouping and order), Dependencies (what blocks what), PRD Coverage (every decision mapped to the story or audit item that discharges it), Bugs (defect record), Spikes (timeboxed unknowns), Baseline (the measurement record), Advocate Behaviour (the 28-tenet implementation audit and improvement plan), Summary (roll-ups).
A6: Team assumption | B6: Solo. One sequential track; dependencies are hard, not advisory.
A8: Definition of done | B8: From PRD E7 and E8, not a generic one. A story is done when its invariant test EXISTS AND HAS RUN, and - for anything on a served path - when it has been verified live in the browser and the answer read. A test that has never run does not count as a test.
A9: Status vocabulary | B9: decided -> built -> tested -> verified live. Nothing is reported above 'built' without naming the test that supports it and when it last ran.
A11: Estimation - read this | B11: Points are Fibonacci (1,2,3,5,8,13). Anything at 13 is a candidate to split or turn into a spike. Points alone will mislead on this project and there is direct evidence: on the s.49 gap, three confident diagnoses in a row were wrong and each was excluded only by instrumenting stage by stage. An '8-point retrieval fix' was really a 1 or a 40 depending on where the cause actually sat.
A12: Uncertainty class | B12: Known - size is a real estimate. Needs measurement - size is a guess until a measurement lands. Unknown until instrumented - do NOT trust the number; run the spike first. Phase 4 onward is estimated on foundations that are not yet measured, so treat those points as provisional by default.
A13: Ordering key | B13: Order is driven by 'What it unlocks', not by effort. The manifest is early because until it exists every later retrieval measurement is uninterpretable. Verification is early because it is the only structure that turns grounding from a prompt instruction into a property of the data path.
A15: Not in this plan | B15: Sprint dates and velocity. There is no throughput data yet, and fake sprint boundaries would be theatre. Milestones are ordered; cadence is yours to set once real throughput exists.
A16: Test classes | B16: A = pure logic, no corpus, no LLM, every commit. B = structural, asserted at runtime on every real turn. C = corpus, on every ingest or index change. D = judgement, rubric and a judge model, approved runs only.
A17: Standing constraint | B17: Golden and end-to-end evaluations are never run without explicit per-run approval, including targeted re-runs.

Sheet Backlog
A1: ID | B1: Phase | C1: Epic | D1: Story | E1: Type | F1: PRD rules | G1: Arch | H1: Pts | I1: Uncertainty | J1: Depends on | K1: What it unlocks | L1: Acceptance - the test | M1: Test class | N1: Status | O1: What was built | P1: Evidence | Q1: Completed
A2: F-01 | B2: Phase 0 - Foundation | C2: EP-01 | D2: Split the repo into core / ports / adapters / knowledge / edge / obs | E2: Infra | F2: P1 | G2: 9.1 | H2: 3 | I2: Known | K2: Every later story can state which layer it belongs to | L2: Directory structure exists; every module has a declared layer | M2: A | N2: tested | O2: nm/ layer tree: core, ports, adapters, knowledge, edge, obs, tools, with tests split by PRD test class. Legacy tree left in place and runnable, deliberately. | P2: nm/tests/a_logic/test_layering.py (ran 2026-08-27) | Q2: 2026-08-27
A3: F-02 | B3: Phase 0 - Foundation | C3: EP-01 | D3: CI rule: core may import only core and ports; violation fails the build | E3: Infra | F3: P1 | G3: 9.1 | H3: 2 | I3: Known | J3: F-01 | K3: Class-A cadence becomes durable rather than aspirational | L3: A commit adding an adapter import to core/ fails CI | M3: A | N3: tested | O3: nm/tools/layercheck.py: AST check of layer rules AND the legacy boundary, in every layer. core/ports/obs proved stdlib-only. Wired into CI as a build failure, not a warning. | P3: nm/tests/a_logic/test_layering.py (ran 2026-08-27) | Q3: 2026-08-27
A4: F-03 | B4: Phase 0 - Foundation | C4: EP-01 | D4: Class-A test runner: no corpus, no LLM, whole suite under 10s | E4: Eval | F4: E1,E2 | G4: 9.2 | H4: 3 | I4: Known | J4: F-01 | K4: Every pure-logic PRD rule becomes enforceable at commit time | L4: Suite runs on every commit and completes under 10s with no network | M4: A | N4: tested | O4: Class-A suite enforces its own preconditions: sockets disabled for the session, legacy imports raise, 10s budget fails the run. 76 tests currently at 0.21s. | P4: nm/tests/a_logic/test_class_a_guarantees.py (ran 2026-08-27) | Q4: 2026-08-27
A5: F-04 | B5: Phase 0 - Foundation | C5: EP-01 | D5: Class-B runtime assertion framework writing to TurnMetrics.violations | E5: Eval | F5: E3 | G5: 10.2 | H5: 5 | I5: Known | J5: F-01,D-01 | K5: Every real turn becomes a test at no extra cost | L5: An asserted invariant failure appears in TurnMetrics and does not block the answer | M5: A | N5: tested | O5: nm/obs/invariants.py: require() records and ships, require_grounded() blocks. The rule's FAMILY decides policy, not the call site. Rule registry makes violations self-describing; an unregistered id logs at ERROR and records against OBS-1 without blocking. | P5: nm/tests/a_logic/test_obs.py (ran 2026-08-27) | Q5: 2026-08-27
A6: F-05 | B6: Phase 0 - Foundation | C6: EP-01 | D6: Class-C corpus test runner | E6: Eval | F6: E1 | G6: 9.2 | H6: 3 | I6: Known | J6: F-01 | K6: Corpus and retrieval quality become repeatable measurements | L6: Runner executes against a corpus snapshot and reports pass/fail per check | M6: A | N6: tested | O6: Class-C conftest: corpus fixture requiring a VERSION stamp (G21). A missing corpus SKIPS rather than fails, and the skip is reported - green with everything skipped must not read as green with everything passing. | P6: nm/tests/c_corpus/test_corpus_identity.py (ran 2026-08-27) | Q6: 2026-08-27
A7: F-06 | B7: Phase 0 - Foundation | C7: EP-01 | D7: Class-D rubric harness using a judge model distinct from the answering model | E7: Eval | F7: E4 | G7: 11 | H7: 5 | I7: Needs measurement | J7: F-05 | K7: Judgement-grade rules can be measured without correlated blind spots | L7: Judge model is configurably different; rubric cases are drawn from sampled real sessions | M7: D | N7: tested | O7: nm/obs/judgement.py: judge model must differ from the answering model (E4); case-set provenance required and authored sets refused (C5D); runs are proposed with a stated cost and authorise() refuses without an approval naming THIS run (E5). | P7: nm/tests/a_logic/test_foundation.py (ran 2026-08-27) | Q7: 2026-08-27
A8: F-07 | B8: Phase 0 - Foundation | C8: EP-01 | D8: Baseline record, seeded with the measurements already taken | E8: Eval | F8: E6 | G8: 10 | H8: 2 | I8: Known | J8: F-08 | K8: 'Did this get worse' becomes answerable | L8: File holds current value, date and method for every measured quantity | M8: A | N8: tested | O8: nm/obs/baseline.py + baseline.json: 16 measured quantities with per-quantity direction, so verdicts follow intent not arithmetic. Informational quantities never read as improved or regressed. move() requires a non-blank reason (E6). | P8: nm/tests/a_logic/test_obs.py (ran 2026-08-27) | Q8: 2026-08-27
A9: F-08 | B9: Phase 0 - Foundation | C9: EP-01 | D9: Turn metrics: latency, call count, tokens, model mix, per-stage timings | E9: Infra | F9: D2B,E6 | G9: 7.13 | H9: 3 | I9: Known | J9: F-01 | K9: Cost regressions become detectable; D2B becomes enforceable | L9: Every turn writes a complete TurnMetrics row | M9: A | N9: tested | O9: nm/obs/metrics.py: TurnMetrics + TurnRecorder behind a ContextVar. Stage timings accumulate rather than overwrite; metrics recorded even when the turn raises; a failing sink never fails the turn. Replaces log-line timings that nothing collected. | P9: nm/tests/a_logic/test_obs.py (ran 2026-08-27) | Q9: 2026-08-27
A10: F-09 | B10: Phase 0 - Foundation | C10: EP-01 | D10: Status tracking: decided / built / tested / verified live | E10: Infra | F10: E7,E8 | G10: 12 | H10: 2 | I10: Known | J10: F-03 | K10: Progress claims become falsifiable | L10: Each PRD decision carries a status and the test that supports it | M10: A | N10: tested | O10: nm/core/status.py: the E7 ladder as an ordered enum. Anything above `built` requires the test AND when it last ran, enforced at construction. highest_claimable() is conservative - offline green is `tested`, never `verified live`. | P10: nm/tests/a_logic/test_foundation.py (ran 2026-08-27) | Q10: 2026-08-27
A11: F-10 | B11: Phase 0 - Foundation | C11: EP-01 | D11: Error policy: programming errors caught separately and logged at ERROR with traceback | E11: Infra | F11: P5 | G11: 10.3 | H11: 3 | I11: Known | J11: F-01 | K11: A NameError stops looking like a model failure | L11: A deliberate NameError in a handler surfaces at ERROR with a traceback, not a warning | M11: A | N11: tested | O11: nm/core/errors.guard() names expected failures and lets programming errors through with a traceback. nm/tools/exceptcheck.py makes it a build step (guard / re-raise / fail-open reason). Found a real violation in metrics.py on first run. | P11: nm/tests/a_logic/test_foundation.py (ran 2026-08-27) | Q11: 2026-08-27
A12: F-11 | B12: Phase 0 - Foundation | C12: EP-01 | D12: Prompt ownership registry: exactly one owner per step, no duplicated text | E12: Infra | F12: - | G12: 10.5 | H12: 3 | I12: Known | J12: F-01 | K12: A prompt change lands everywhere it should, by construction | L12: No prompt string appears in two modules; a change to a step's prompt has one site | M12: A | N12: tested | O12: nm/core/steps.py: one owner per prompt. Duplicate prompt text is refused, with a whitespace-normalised fingerprint because reformatting is how the second owner appears. | P12: nm/tests/a_logic/test_foundation.py (ran 2026-08-27) | Q12: 2026-08-27
A13: F-12 | B13: Phase 0 - Foundation | C13: EP-01 | D13: Per-step model policy declaration; cheap model is the default | E13: Infra | F13: D2B | G13: 10.6 | H13: 2 | I13: Known | J13: F-08 | K13: model_mix becomes derivable without scattered instrumentation | L13: Every LLM-calling step declares its model and the reason if it is not the cheap one | M13: A | N13: tested | O13: nm/core/steps.py: cheap model is the default; strong requires a justification naming the measurement. strong_model_report() is what a cost review reads (D2B). | P13: nm/tests/a_logic/test_foundation.py (ran 2026-08-27) | Q13: 2026-08-27
A14: D-01 | B14: Phase 0 - Foundation | C14: EP-02 | D14: Core entity definitions from the information view | E14: Core | F14: - | G14: 7 | H14: 8 | I14: Known | J14: F-01 | K14: Every rule gets somewhere to live | L14: All entities in ARCHITECTURE 7 exist as types with non-optional fields as specified | M14: A | N14: tested | O14: re-affirmed after review fixes | P14: nm/tests/a_logic/test_entities.py (ran 2026-08-27) | Q14: 2026-08-27
... A40: I-02 | B40: Phase 1 - Knowledge | C40: EP-05 | D40: Judgment ingestion with paragraph classification | E40: Knowledge | F40: C3 | G40: 5 | H40: 8 | I40: Known | J40: K-01 | K40: Attribution to the court becomes possible | L40: Every paragraph carries a kind; unclassified is explicit, not absent | M40: C | N40: tested | O40: nm/knowledge/judgments.py::_ascending_run (B-63). A marker's span is evidence about its own paragraph and nothing more. Measured, a 2022 Supreme Court judgment offered the markers 1, 2, 3, 366, 4 - the 366 a citation fragment - and 366's span ran 4,251 characters to the next marker while the true paragraph 4 held 576, so the chain 1,2,3,366 outweighed 1,2,3,4 and 60% of the judgment became one 'paragraph 366' carrying one kind and one attribution. That is a C3 problem, not a tidiness one. A document with five markers has no paragraphs 4 to 365, so a number larger than the count of markers cannot be a paragraph index: it is not rejected, it is simply not paid for the text it swallowed, and where two readings then weigh the same the one whose numbering counts its own paragraphs wins. The cap is deliberately narrow - requiring 1, 2, 3 was tried and one hidden marker truncated whole chains (B-62). Measured over 300 judgments: the final paragraph shrank in 37 and grew in 2, releasing 389,262 characters. Residue: judgments with no numbering at all, where one block is an honest reading. | P40: nm/tests/a_logic/test_judgments.py::test_a_number_that_cannot_be_a_paragraph_index_is_not_paid_for_what_it_swallowed, ::test_a_sparsely_numbered_judgment_is_not_truncated_by_the_same_rule (ran 2026-08-28) | Q40: 2026-08-28
A41: I-03 | B41: Phase 1 - Knowledge | C41: EP-05 | D41: Ingest Telangana High Court, 2019 onward | E41: Knowledge | F41: D3A | G41: 5 | H41: 13 | I41: Unknown until instrumented | J41: I-02 | K41: The binding court for the jurisdiction stops being absent | L41: Manifest shows non-zero Telangana HC coverage for 2019 onward | M41: C | N41: decided
A42: I-04 | B42: Phase 1 - Knowledge | C42: EP-05 | D42: Classification pass over unclassified paragraphs | E42: Knowledge | F42: C3 | G42: 5 | H42: 8 | I42: Needs measurement | J42: I-02 | K42: A quarter of the case corpus moves from unusable to attributable | L42: Unknown share is reported after the pass; residue keeps the interim rule | M42: C | N42: built | O42: nm/knowledge/classify.py - the pass's plan and result type. A low-confidence reading stays UNKNOWN, and a residue of zero is treated as a DEFECT signal rather than a win. Cost measured on a spread sample and scaled: ~250,398 unclassified paragraphs, ~114.5M input tokens. Not run - E5 requires approval. | P42: nm/tests/a_logic/test_classify.py (8 class-A rules) (ran 2026-08-27) | Q42: 2026-08-27
A43: I-05 | B43: Phase 1 - Knowledge | C43: EP-05 | D43: Era metadata: commencement and repeal dates on ingest | E43: Knowledge | F43: D3B,G1 | G43: 5 | H43: 5 | I43: Known | J43: K-02 | K43: Point-in-time resolution gets its inputs | L43: Every ingested provision carries commencement and, where applicable, repeal | M43: C | N43: tested | O43: nm/knowledge/sources.py - an Act is named by what it STATES, not by what it is filed as (B-60, B-42). A filename is a lossy rendering of a title: the filesystem cannot hold a slash, so `Municipal Councils/Nagar Panchayats` is filed as `CouncilsNagar` and keys to a different subject. Measured, 60 of 1,655 raw files carry a filename naming a different Act than the document does - sixty times what the defect recorded - and one of them took its name from a definition clause forty lines into the text. The title is read STRUCTURALLY, as the line above the instrument-number line where both scrape templates put it, rather than by pattern: the worst-keyed Act ends in a bare year and matches no reasonable title regex, and it is exactly the file whose name came from a definition clause. 1,613 of 1,655 state a title; the remaining 42 keep the filename and say so, so no subject is silently keyed on the weaker source. Zero-width encoding artefacts are stripped wherever a raw value is read: a byte-order mark is invisible, so two titles differing only by one look identical and compare unequal. | P43: nm/tests/a_logic/test_sources_title.py (6 tests); nm/tests/c_corpus/test_source_titles.py::test_the_act_named_from_a_definition_clause_is_keyed_on_its_real_title (ran 2026-08-28) | Q43: 2026-08-28
A44: I-06 | B44: Phase 1 - Knowledge | C44: EP-05 | D44: Idempotent ingest with deduplication | E44: Knowledge | F44: - | G44: 5 | H44: 5 | I44: Known | J44: I-01 | K44: Re-ingestion stops silently duplicating the corpus | L44: Re-running ingestion over the same source changes nothing | M44: C | N44: tested | O44: Ingestion is a pure fold over a sorted input, so re-running cannot duplicate: verified identical across two runs. Deduplication resolves 16,956 ids claimed by more than one provision - a section printing a second lettered list, and two files keying to one subject - by keeping the fuller text, which is the union-preserving choice measured in subject.py. Every discarded copy is reported. | P44: test_ingest_corpus.py::test_re_running_ingestion_over_the_same_source_changes_nothing (ran 2026-08-27) | Q44: 2026-08-27
A45: I-07 | B45: Phase 1 - Knowledge | C45: EP-05 | D45: Artefact identity stamping on every derived store | E45: Knowledge | F45: G21 | G45: 10.4 | H45: 3 | I45: Known | J45: I-06 | K45: Staleness becomes detectable across all derived artefacts | L45: Every index, store and summary records what it was built from | M45: C | N45: tested | O45: nm/knowledge/artefact.py - one owner for G21. An artefact cannot be constructed without naming its inputs, and the builder is part of the identity so a store rebuilt by a changed prompt is a different artefact even when every input byte matches. Generalises the rule that previously existed separately on the graph and the manifest. | P45: nm/tests/a_logic/test_artefact.py (9 class-A rules) (ran 2026-08-27) | Q45: 2026-08-27
A46: I-08 | B46: Phase 1 - Knowledge | C46: EP-05 | D46: Stale-artefact refusal | E46: Knowledge | F46: G21 | G46: 10.4 | H46: 3 | I46: Known | J46: I-07 | K46: A stale index stops serving old results silently | L46: An artefact older than its source is refused, not used | M46: C | N46: tested | O46: Identity.require_current refuses rather than warns, and the refusal names what changed, what vanished and what is present but was not built from. Bounded so an artefact is judged only against the inputs it declared - an index over the Acts is not refused because the case store moved. | P46: nm/tests/a_logic/test_artefact.py::test_an_artefact_whose_source_changed_is_refused_not_warned_about and peers (ran 2026-08-27) | Q46: 2026-08-27
A47: I-09 | B47: Phase 1 - Knowledge | C47: EP-05 | D47: Close the thinly-ingested Acts, intended subjects first | E47: Knowledge | F47: D5A,M4,D4 | G47: 10.4 | H47: 13 | I47: Needs measurement | J47: I-01,M-03 | K47: Coverage claims become true at section granularity, so a refusal is honest and a gap is nameable | L47: No manifest subject reports sections absent below the highest it holds; the residue is disclosed with a reason per Act rather than counted | M47: C | N47: tested | O47: nm/knowledge/gaps.py - per-Act disclosure joining numbering holes to the refusal records ingestion writes, so a hole carries the reason it exists instead of being counted. Over 1,641 Acts: 1,479 contiguous, 162 with something absent, 205 holes carrying a reason and 144 honest residue. Intended manifest subjects lead the backlog whatever their hole counts. | P47: nm/tests/a_logic/test_gaps.py (7 class-A rules) (ran 2026-08-27) | Q47: 2026-08-27
A48: I-10 | B48: Phase 1 - Knowledge | C48: EP-05 | D48: Section identifiers parsed as identifiers, not as any number on the line | E48: Knowledge | F48: D5A,G1 | G48: 7 | H48: 5 | I48: Known | J48: I-01 | K48: A provision id addresses the provision; numbering integrity becomes a usable coverage signal instead of noise | L48: No Act has a numbering gap wider than the count of sections it holds; a number that cannot be parsed as an identifier fails ingestion rather than being stored | M48: C | N48: tested | O48: Section identifiers are parsed as identifiers: a candidate opening a gap out of scale with the numbering the Act itself holds is refused with its reason and locator, never stored. Acts carrying an out-of-scale gap fell from 312 to 23, and the residue is Acts holding fewer than three identifiers, where no outlier test has a spread to work with. 174 identifiers refused across the tree. | P48: test_ingest.py::test_an_identifier_the_acts_own_numbering_cannot_hold_is_refused; test_ingest_corpus.py::test_no_act_holds_a_numbering_gap_wider_than_its_own_section_count (ran 2026-08-27) | Q48: 2026-08-27
A49: X-01 | B49: Phase 1 - Knowledge | C49: EP-06 | D49: Lexical index build | E49: Knowledge | F49: G3 | G49: 5 | H49: 5 | I49: Known | J49: I-01 | K49: Exact matching on section numbers and defined terms | L49: Index built, versioned and reconciled against source counts | M49: C | N49: tested | O49: nm/knowledge/index.py - BM25 over 291,359 provisions, 48,110 terms, built in 8s and reconciled against its source count. An unseen term contributes nothing rather than a penalty. Article 59 now ranks FIRST for 'cancel or set aside an instrument' - the provision measured at rank 53 of 60 in the original defect. | P49: nm/tests/a_logic/test_index.py (9 class-A rules) (ran 2026-08-27) | Q49: 2026-08-27
A50: X-02 | B50: Phase 1 - Knowledge | C50: EP-06 | D50: Dense index build | E50: Knowledge | F50: G3 | G50: 5 | H50: 5 | I50: Known | J50: I-01 | K50: Paraphrase matching | L50: Index built, versioned and reconciled | M50: C | N50: tested | O50: nm/knowledge/embed.py - dense index built on GPU: 284,447 provisions embedded with all-MiniLM-L6-v2 in 509s, 384 dimensions, stamped with an Identity whose builder carries the model so a store built by a different checkpoint is refused rather than blended. Skips 995 provisions with no text and 5,917 too short to carry meaning. hybrid() fuses lexical and dense on RANK (RRF), not on score - measured, BM25 runs 20-34 and cosine 0-1, so adding them let the lexical leg swamp the dense one entirely. Fusion decides order and never membership: the lexical tail is appended below the fused head. | P50: nm/tests/a_logic/test_index.py (12 class-A rules incl. dense counting, encoder refusal, fusion membership) (ran 2026-08-27) | Q50: 2026-08-27
A51: X-03 | B51: Phase 1 - Knowledge | C51: EP-06 | D51: Section-level summaries | E51: Knowledge | F51: G20 | G51: 5 | H51: 8 | I51: Known | J51: I-01 | K51: The missing middle granularity | L51: Every section has a summary carrying its source identity | M51: C | N51: built | O51: nm/knowledge/summaries.py - Summary type carrying its source digest, section-level per G20. Cost measured and proposed, not initiated: 67,315 sections, ~17.2M input tokens on the cheap model. No summaries generated - E5 requires a bulk run to be approved. | P51: nm/tests/a_logic/test_summaries.py (11 class-A rules) (ran 2026-08-27) | Q51: 2026-08-27
A52: X-04 | B52: Phase 1 - Knowledge | C52: EP-06 | D52: Holding summaries: what a judgment decided, on what facts | E52: Knowledge | F52: G19 | G52: 5 | H52: 13 | I52: Unknown until instrumented | J52: I-02 | K52: On-point-ness gets a representation, so weight stops winning by default | L52: Every judgment has a holding summary distinct from its subject summary | M52: C | N52: built | O52: Holding summaries are a separate TYPE from subject summaries so one cannot stand for the other - a system holding only subject summaries has no representation of on-point-ness and citation weight wins by default. Cost measured on a spread sample and scaled: ~30,236 judgments, ~210M input tokens. Not run. | P52: nm/tests/a_logic/test_summaries.py::test_the_two_kinds_are_separate_types_so_one_cannot_stand_for_the_other (ran 2026-08-27) | Q52: 2026-08-27
A53: X-05 | B53: Phase 1 - Knowledge | C53: EP-06 | D53: Summary provenance and staleness refusal | E53: Knowledge | F53: G21 | G53: 10.4 | H53: 3 | I53: Known | J53: X-03,I-08 | K53: A fluent stale summary stops being invisible | L53: A summary whose source changed is refused until regenerated | M53: C | N53: tested | O53: A summary carries the digest of the exact provision text it was written from and is refused when that text changes - finer than store-level identity, because a summary goes stale one provision at a time. Staleness is reported per summary so one amended section costs one summary rather than the store. | P53: nm/tests/a_logic/test_summaries.py::test_a_summary_whose_source_changed_is_refused and peers (ran 2026-08-27) | Q53: 2026-08-27
... A171: AN-09 | B171: Phase 4 - Delivery | C171: EP-22 | D171: Summary as single source; board and answer derive | E171: Core | F171: CS1 | G171: 7.15 | H171: 3 | I171: Known | J171: AN-07,AN-08 | K171: Board and answer stop being able to disagree | L171: Neither holds anything the summary does not | M171: B | N171: tested | O171: nm/edge/board.py::Board.of + nm/edge/phase4.py::assert_answer_derives_from_summary - the board is derived by construction (its only filling constructor reads a CaseSummary), and the answer's refs are checked against the summary's known_refs. | P171: nm/tests/a_logic/test_phase4_answer.py::test_the_board_can_hold_nothing_the_summary_does_not, ::test_an_answer_citing_what_the_summary_does_not_hold_is_reported (ran 2026-08-28) | Q171: 2026-08-28
A172: AN-10 | B172: Phase 4 - Delivery | C172: EP-22 | D172: Summary reads as a case note, not a debug dump | E172: Edge | F172: CS5 | G172: 7.15 | H172: 3 | I172: Known | J172: AN-08 | K172: The advocate can take it into a conference | L172: No identifiers, scores or pipeline state | M172: D | N172: built | O172: nm/core/summary.py::render_case_note, identifier_leaks - the MECHANICAL half of CS5 is tested: no internal identifier reaches the case note, checked exactly against internal_ids because the ids are known. DOWNGRADED from tested after review. AN-10 is a Class D story and its acceptance ('reads as a case note, not a debug dump') is a judgement criterion that has not run - E5 requires per-run approval and E8 says a test that never ran is not a test. This now matches the Phase 3 precedent, where 13 Class D stories stayed BUILT for exactly this reason. | Q172: 2026-08-28
A173: AN-11 | B173: Phase 4 - Delivery | C173: EP-22 | D173: Inference labelling distinct from citation | E173: Core | F173: D5 | G173: 7.15 | H173: 5 | I173: Known | J173: V-01,AN-01 | K173: Reasoning becomes auditable without being forbidden | L173: Every inference marked; no inference carries a citation as though a proposition | M173: B | N173: tested | O173: nm/core/answer.py::Element + nm/core/assembly.py::render_element - an inference carries PREMISES and structurally cannot carry refs, cannot be a GROUND, and cannot exist unmarked. D5's most dangerous output - an inference dressed as a citation - is made unrepresentable rather than forbidden. | P173: nm/tests/a_logic/test_phase4_answer.py::test_an_inference_cannot_carry_a_citation_as_though_it_were_a_proposition, ::test_an_inference_cannot_be_a_ground, ::test_premises_without_the_label_are_refused (ran 2026-08-28) | Q173: 2026-08-28
A174: DF-01 | B174: Phase 5 - Drafting | C174: EP-23 | D174: DrafterBrief contract | E174: Core | F174: DR1 | G174: 6 | H174: 5 | I174: Known | J174: AN-08 | K174: Re-extraction, where facts get invented, becomes unnecessary | L174: Structured fields, not prose | M174: A | N174: tested | O174: nm/core/brief.py::DrafterBrief - DR1's field list as a typed contract, no free-text field carrying facts, undated facts kept out of the chronology rather than given a position (L3). Unchanged by the review. | P174: nm/tests/a_logic/test_phase5_drafting.py::test_every_fact_crossing_the_boundary_carries_its_provenance, ::test_the_brief_has_no_free_text_field_that_could_carry_a_fact (ran 2026-08-28) | Q174: 2026-08-28
A175: DF-02 | B175: Phase 5 - Drafting | C175: EP-23 | D175: Brief assembly from analysis | E175: Core | F175: DR1 | G175: 6 | H175: 8 | I175: Known | J175: DF-01,TH-01,PF-01 | K175: Drafting gets everything it needs and nothing it should not have | L175: All contract fields populated from matter state | M175: B | N175: tested | O175: nm/core/brief.py::assemble_brief - built from the case summary, refused while a blocking gate is open. HARDENED after review, where 'derives from the summary' turned out to be a claim about intent rather than a property of the code: findings were an arbitrary iterable and are now checked against position.known_refs (CS1); unconfirmed facts reached the pleadable set and are now refused by name (D10); and the cause title INVENTED 'the applicant' / 'the respondent' when parties were absent, which is fluent completion arriving before the drafter - ours and theirs are now required arguments, as is confirmation_threshold. | P175: nm/tests/a_logic/test_phase5_drafting.py::test_the_brief_refuses_an_authority_the_summary_does_not_hold, ::test_an_unconfirmed_fact_cannot_be_pleaded, ::test_the_cause_title_parties_cannot_be_invented (ran 2026-08-28) | Q175: 2026-08-28
A176: DF-03 | B176: Phase 5 - Drafting | C176: EP-23 | D176: Drafting agent as a separate process that cannot retrieve | E176: Adapter | F176: DR2 | G176: 6 | H176: 5 | I176: Known | J176: DF-01 | K176: One audit chain is preserved | L176: The drafter has no retrieval capability; missing law is a request back | M176: A | N176: built | O176: nm/drafting/ as a layer with no access to nm.evidence or nm.knowledge (layercheck), a signature with nowhere to put a retriever, a Composition that cannot exceed the brief, and retrieval_in_reach() which inspects the composer's closure and module globals before it runs. DOWNGRADED from tested after review. The story is 'drafting agent as a SEPARATE PROCESS'; what exists is a layer and signature boundary inside one process. The reach check catches mistakes - a captured retrieval client, a retrieval import in the composer's module - and cannot catch intent: a dynamic import inside the call, a C extension, an attribute off a handed object. ADR-8's process split is what would enforce DR2 against intent, and it is not built. | P176: nm/tests/a_logic/test_phase5_drafting.py::test_a_composer_that_can_reach_retrieval_is_refused_before_it_runs, ::test_the_reach_check_does_not_refuse_the_legitimate_supplier (ran 2026-08-28) | Q176: 2026-08-28
A177: DF-04 | B177: Phase 5 - Drafting | C177: EP-23 | D177: Averment traceability to brief facts | E177: Core | F177: DR3 | G177: 6 | H177: 8 | I177: Known | J177: DF-02 | K177: An unsupported averment stops being filable | L177: Every averment traces to a fact with provenance | M177: B | N177: tested | O177: nm/drafting/draft.py::Averment - an averment cannot be constructed resting on nothing, and Draft carries its BRIEF as a field rather than receiving it at check time. That removes the state the legacy verifier reported as a pass: there is no draft for which the tracing check has nothing to check. Formal text is exempt, because forcing a citation onto 'the plaintiff submits as follows' is a rule that makes the output worse. | P177: nm/tests/a_logic/test_phase5_drafting.py::test_an_averment_resting_on_nothing_cannot_be_built, ::test_a_draft_cannot_be_separated_from_its_brief, ::test_an_averment_on_a_fact_the_brief_does_not_hold_is_caught, ::test_formal_text_is_not_required_to_trace (ran 2026-08-28) | Q177: 2026-08-28
A178: DF-05 | B178: Phase 5 - Drafting | C178: EP-23 | D178: Not-to-plead list travels with the brief | E178: Core | F178: DR4 | G178: 6 | H178: 3 | I178: Known | J178: DF-01,SE-01 | K178: The drafter stops helpfully restoring what was deliberately excluded | L178: Excluded facts and their reasons are in the brief | M178: B | N178: tested | O178: nm/core/brief.py::ExcludedFact + nm/drafting/verify.py::_exclusions_respected - the not-to-plead list travels with the brief and every exclusion carries its reason. The legacy tree has no equivalent field anywhere, so DR4 was absent rather than weak. Verification catches an averment that rests on an excluded fact. | P178: nm/tests/a_logic/test_phase5_drafting.py::test_an_exclusion_must_carry_its_reason, ::test_a_draft_that_restores_an_excluded_fact_is_caught, ::test_an_excluded_fact_does_not_reach_the_pleadable_set (ran 2026-08-28) | Q178: 2026-08-28
A179: DF-06 | B179: Phase 5 - Drafting | C179: EP-23 | D179: Draft verified against its brief before it is shown | E179: Core | F179: DR5 | G179: 6 | H179: 8 | I179: Known | J179: DF-04 | K179: Drafting gets its stricter gate | L179: Every averment traced, every citation in force and binding, every date matched | M179: B | N179: tested | O179: nm/drafting/verify.py - nine mechanical checks with a three-state outcome where could-not-run BLOCKS. CORRECTED after review found FOUR confirmed false passes, all one mistake: _discloses asked whether an authority's reference appeared anywhere in the prose, so citing a persuasive authority counted as disclosing that it was persuasive, citing an overruled judgment counted as disclosing the treatment, and naming the limitation Article counted as pleading compliance. A fifth node kind, Disclosure, now names its subject and kind so the question is an exact lookup - the model changed rather than the check getting cleverer. | P179: nm/tests/a_logic/test_phase5_drafting.py::test_a_citation_is_not_a_disclosure_of_what_is_being_cited, ::test_naming_the_article_is_not_pleading_the_compliance_plea, ::test_a_check_that_could_not_run_does_not_clear (ran 2026-08-28) | Q179: 2026-08-28
A180: DF-07 | B180: Phase 5 - Drafting | C180: EP-23 | D180: Gaps marked as blanks, never filled | E180: Core | F180: DR6 | G180: 6 | H180: 5 | I180: Known | J180: DF-02 | K180: The highest-risk drafting failure becomes structurally prevented | L180: A draft with no blanks on a file with open gaps is a defect | M180: B | N180: tested | O180: nm/drafting/draft.py::Blank - a blank is a NODE, not a string convention. The legacy tree asked a model for [GAP: ...] in a prompt and stripped unresolved tags at render time, which is the one operation that turns a visible hole invisible. Blanks are computed from the brief's open gaps and appended by the drafter, so they are not the composer's to tidy; set equality is checked BOTH ways, so a hole cannot be dropped or invented. | P180: nm/tests/a_logic/test_phase5_drafting.py::test_a_draft_with_no_blanks_on_a_file_with_open_gaps_is_a_defect, ::test_a_blank_cannot_be_invented_any_more_than_it_can_be_filled, ::test_the_drafter_supplies_owed_blanks_the_composer_left_out (ran 2026-08-28) | Q180: 2026-08-28
A181: DF-08 | B181: Phase 5 - Drafting | C181: EP-23 | D181: Drafter does not re-decide ranked reliefs or selected arguments | E181: Core | F181: DR7 | G181: 6 | H181: 2 | I181: Known | J181: DF-02 | K181: Judgement stays in the component held to the advising standard | L181: The draft follows the brief's ranking | M181: B | N181: tested | O181: nm/drafting/verify.py::_reliefs_follow_the_brief + agent.py::RankingObjection - the draft's prayers must equal the brief's relief order as a sequence. CORRECTED after review: Prayer accepted empty text, so a prayer that asked the court for nothing satisfied the ranking comparison. | P181: nm/tests/a_logic/test_phase5_drafting.py::test_the_draft_follows_the_briefs_ranking, ::test_a_prayer_must_carry_the_text_that_is_actually_filed (ran 2026-08-28) | Q181: 2026-08-28
A182: EN-01 | B182: Phase 6 - Enterprise | C182: EP-24 | D182: Accounts and advocate identity | E182: Enterprise | F182: - | G182: 5 | H182: 8 | I182: Known | J182: F-01 | K182: Multi-user becomes possible | L182: Sign-in, identity, session lifecycle | M182: B | N182: built | O182: nm/core/identity.py - Advocate, Chambers and Session with the lifecycle COMPUTED rather than stored, so a session cannot report itself active after it expired. Advocate is deliberately thin: no email, no client-identifying field, because the way personal data reaches a diagnostics store is by riding on a value nobody thought of as personal. NOT DONE: sign-in itself - credentials, token issue, reset - which needs an adapter and an edge that do not exist. Identity and lifecycle are tested; the story is not. | Q182: 2026-08-28
A183: EN-02 | B183: Phase 6 - Enterprise | C183: EP-24 | D183: Matter isolation and access control | E183: Enterprise | F183: - | G183: 5 | H183: 8 | I183: Known | J183: EN-01 | K183: One advocate's file becomes inaccessible to another | L183: Access is denied by default and granted explicitly | M183: B | N183: tested | O183: nm/core/identity.py - two holes closed after a counterexample review. (1) Grant.is_live checked only revocation, so a grant dated a year ahead authorised an access today: existing as an object was enough. A permission is bounded at BOTH ends or it is not bounded. (2) decide/authorise accepted session=None and skipped every session check, so an unauthenticated caller was an advocate as long as it supplied the right string. `session` is now a required keyword on both, and None DENIES rather than raising - required so it cannot be omitted, denying so the omission fails closed. InMemoryMatterStore takes it through read/write/delete with the same default-is-refusal. | P183: nm/tests/a_logic/test_phase6_enterprise.py::test_access_is_denied_by_default, ::test_a_revoked_grant_stops_permitting_immediately; nm/tests/a_logic/test_phase7_turn.py::test_a_store_read_with_no_session_is_refused (ran 2026-08-28) | Q183: 2026-08-28
A184: EN-03 | B184: Phase 6 - Enterprise | C184: EP-24 | D184: Chambers grouping and controlled sharing | E184: Enterprise | F184: - | G184: 5 | H184: 8 | I184: Known | J184: EN-02 | K184: A junior and a senior can work the same file | L184: Sharing is explicit, revocable and audited | M184: B | N184: tested | O184: nm/core/identity.py::Grant, Chambers, shareable_with - sharing is explicit, revocable and reasoned; a grant with no reason is refused, because an access review works by reading reasons. Chambers MEMBERSHIP IS NOT ACCESS: it is the set a share may be made to, kept as its own function so the distinction is legible at the call site. | P184: nm/tests/a_logic/test_phase6_enterprise.py::test_chambers_membership_is_not_access, ::test_a_grant_must_carry_its_reason, ::test_a_revoked_grant_stops_permitting_immediately (ran 2026-08-28) | Q184: 2026-08-28
A185: EN-04 | B185: Phase 6 - Enterprise | C185: EP-24 | D185: Access audit | E185: Enterprise | F185: - | G185: 5 | H185: 5 | I185: Known | J185: EN-02 | K185: Who saw what becomes answerable | L185: Every access to a matter is recorded | M185: B | N185: tested | O185: nm/core/identity.py::authorise plus its FIRST production caller in nm/edge/session.py::serve. The record is checked against EN-10's guard before it is written and the write still denies on failure. AccessLog now declares __len__ on the port, because EN-04 is asserted by COUNTING the log across the call and a log that cannot be counted is one whose invariant cannot be checked - the obligation belongs on the boundary, not in a caller hoping the adapter supports it. | P185: nm/tests/a_logic/test_phase7_turn.py::test_a_served_turn_records_the_access_and_counts_it, ::test_a_served_turn_is_authorised_before_anything_reads_the_matter (ran 2026-08-28) | Q185: 2026-08-28
A186: EN-05 | B186: Phase 6 - Enterprise | C186: EP-25 | D186: Encryption at rest and in transit | E186: Enterprise | F186: - | G186: 5 | H186: 5 | I186: Known | J186: EN-01 | K186: Client confidentiality gets a technical floor | L186: All matter data and documents encrypted; keys managed | M186: B | N186: built | O186: nm/adapters/crypto.py::EncryptedMatterStore - the first adapter that actually encrypts anything (B-74). The port has reported protection honestly since Phase 6 and nothing implemented it, so PROTECTED was a state nothing could be in. Each of infra/crypto.py's three documented behaviours is inverted: the store cannot exist without a key (no silent no-op), a failed decryption RAISES rather than returning ciphertext as though it were the client's facts, and plaintext residue is counted and refused rather than passed through - so 'the data is encrypted' is a number instead of a claim. AES-256-GCM with the matter id as authenticated data, so a record moved between matters fails rather than decrypting into the wrong file. `open_matter_store(require_encryption=...)` has no default: an unencrypted deployment needs someone's `require_encryption=False` in a diff, not an absent environment variable. HELD AT built, not tested: the acceptance is 'all matter data and documents encrypted; keys managed', and neither half is true of the system - no served path uses this store and there is no key management beyond a per-deployment salt. | Q186: 2026-08-28
A187: EN-06 | B187: Phase 6 - Enterprise | C187: EP-25 | D187: Retention and deletion of client data | E187: Enterprise | F187: - | G187: 5 | H187: 8 | I187: Known | J187: EN-05 | K187: An advocate can honour their own obligations | L187: Deletion is complete, verifiable and covers derived artefacts | M187: B | N187: built | O187: DOWNGRADED from tested, and the code is better than it was. nm/core/retention.py now compares coverage by SET EQUALITY against ERASABLE_STORES - facts, derivations, documents, summaries, exports, indexes, logs, backups - and a store nobody supplied is `not checked`, never clean. The earlier version read two stores, found both clean and reported a complete erasure: a deletion that has looked at a quarter of the system makes a STRONGER claim than one that fails. But the control being honest is not the acceptance. Six of the eight stores exist only as StoreView.empty declarations in a test, no production path performs an erasure, and `deletion is complete` is therefore still a sentence about code rather than about the system. | Q187: 2026-08-28
A188: EN-07 | B188: Phase 6 - Enterprise | C188: EP-25 | D188: Data residency for Indian legal data | E188: Enterprise | F188: - | G188: 5 | H188: 8 | I188: Unknown until instrumented | J188: EN-05 | K188: A residency question stops blocking a sale | L188: Storage and processing locations documented and enforced | M188: C | N188: built | O188: nm/ports/confidentiality.py::Residency + nm/obs/compliance.py::SURFACES - storage and processing regions are NAMED SEPARATELY, because they differ and a claim covering only storage is wrong exactly where it matters. Six surfaces are registered and ALL are undeclared, which is honest: nothing is deployed, and an entry with a region would be a claim about infrastructure that does not exist. NOT DONE: enforcement, which needs adapters that declare their own region. | Q188: 2026-08-28
A189: EN-08 | B189: Phase 6 - Enterprise | C189: EP-25 | D189: DPDP Act posture review | E189: Enterprise | F189: - | G189: 5 | H189: 8 | I189: Unknown until instrumented | J189: EN-06 | K189: Compliance stops being an unknown | L189: Obligations mapped to controls; gaps listed with owners | M189: C | N189: tested | O189: nm/obs/compliance.py::DPDP_REGISTER - nine obligations mapped to controls, with three gaps. An obligation with no control MUST name an owner, and assessed_count() is reported so 'we reviewed our DPDP posture' cannot be said without 'against nine obligations'. An obligation absent from the register is UNASSESSED, not satisfied. CAVEAT: the three open gaps carry owner='unassigned', which satisfies the type and not the intent - real owners are a decision only the practice can take. | P189: nm/tests/a_logic/test_phase6_enterprise.py::test_an_obligation_with_no_control_must_name_an_owner, ::test_the_register_reports_how_many_obligations_it_assessed (ran 2026-08-28) | Q189: 2026-08-28
A190: EN-09 | B190: Phase 6 - Enterprise | C190: EP-25 | D190: Per-matter document storage isolation | E190: Enterprise | F190: - | G190: 5 | H190: 5 | I190: Known | J190: EN-02,DI-01 | K190: A document leak across matters becomes structurally impossible | L190: Storage paths are matter-scoped and access-checked | M190: B | N190: built | O190: nm/ports/confidentiality.py::MatterStore - read/write/delete take the ADVOCATE, not just the matter, because a store whose signature omits the principal cannot enforce EN-02 and the enforcement then has to live in every caller. Path-level matter isolation already exists from DI-01 (nm/adapters/documents.py). NOT DONE: no adapter implements MatterStore, so the access check is a contract with no implementation. | Q190: 2026-08-28
A191: EN-10 | B191: Phase 6 - Enterprise | C191: EP-25 | D191: PII handling in logs, metrics and diagnostics | E191: Enterprise | F191: - | G191: 10.2 | H191: 5 | I191: Known | J191: F-08 | K191: Instrumentation stops becoming a second copy of the client file | L191: No client content in metrics or diagnostics; identifiers only | M191: B | N191: tested | O191: nm/obs/privacy.py - a whitelist over field NAMES cannot keep prose out, and this module proved it: `purpose` and `reason` were permitted because neither is content by definition, so {'purpose': 'client admitted fraud on 12 March'} was reported clean and survived scrub(). A permitted field now declares the SHAPE of value it may hold - ID (no internal whitespace: an identifier that reads like a sentence is not one), NUMBER, TIME, or CODE from a vocabulary the caller DECLARES, where an undeclared vocabulary fails rather than passes. identity.py's audit line carries a ReasonCode and a Purpose enum instead of sentences; the human explanation goes to the human. Then the wiring found a second leak of the same shape: every class-B assertion in phase4/phase6 quoted the offending material into its message (element.text[:60], signal.text[:60], chain.statement[:50]), so the metrics store filled with the client's own words. A violation is a diagnostics record; it now names the gap, thread, element kind or statement position and never the words. | P191: nm/tests/a_logic/test_phase6_enterprise.py::test_client_content_can_never_reach_diagnostics, ::test_scrub_drops_rather_than_masks; nm/tests/a_logic/test_phase7_turn.py::test_a_violation_detail_never_carries_the_words_it_is_complaining_about (ran 2026-08-28) | Q191: 2026-08-28
A192: EN-11 | B192: Phase 6 - Enterprise | C192: EP-26 | D192: Provenance audit trail per statement | E192: Enterprise | F192: QS4 | G192: 12 | H192: 8 | I192: Known | J192: AN-11,V-01 | K192: An advocate can defend where an answer came from | L192: Fact to provenance, law to span, inference labelled, in three steps | M192: B | N192: tested | O192: nm/core/audit.py - Chain.is_complete required only `no unresolved refs and at least one step`, so an element referring to nothing produced a one-step chain reporting a COMPLETE three-step audit. `Nothing to resolve` is not `resolved`: that is the two-state failure this build keeps finding, arriving in the module written to detect it. Steps now carry a StepRole and completeness is set equality against all three roles, which states EN-11's rule rather than this implementation's step count. Four states (complete / unsupported / unresolved / not required) with the bound stated: a QUESTION asserts nothing, so demanding provenance for one would be the guard rejecting correct output. Wired into serve, where it immediately reported the two unsupported statements in a real turn. | P192: nm/tests/a_logic/test_phase6_enterprise.py::test_a_statement_resting_on_nothing_is_not_a_complete_audit, ::test_a_question_is_not_held_to_a_provenance_it_cannot_have (ran 2026-08-28) | Q192: 2026-08-28
A193: EN-12 | B193: Phase 6 - Enterprise | C193: EP-26 | D193: Matter export with advice, citations and provenance | E193: Enterprise | F193: - | G193: 12 | H193: 8 | I193: Known | J193: EN-11 | K193: The work product leaves the product intact | L193: Export renders the case note, authorities and provenance | M193: B | N193: tested | O193: nm/edge/export.py - `an export covers one matter` was a sentence in a docstring and a heading on the document. Nothing compared `matter` to the summary being rendered or to the chains and findings supplied, so an export labelled m-1 assembled from another matter's material produced a clean, complete, well-formed document containing a second client's case note: every part correct except which file it came from. CaseSummary now names its matter (the refusal TurnHistory already made about a foreign entry), an authority reaches the document only if the summary vouches for it, and a chain only if everything it walks is in the same set. Anything else is HELD BACK and named - held back rather than raised because an advocate needs the document, named rather than dropped because a document that quietly omitted something is one nobody can rely on either. | P193: nm/tests/a_logic/test_phase6_enterprise.py::test_an_export_cannot_be_headed_one_matter_and_filled_with_another, ::test_material_the_case_note_does_not_hold_is_held_back_and_named (ran 2026-08-28) | Q193: 2026-08-28
A194: EN-13 | B194: Phase 6 - Enterprise | C194: EP-26 | D194: Immutable turn history | E194: Enterprise | F194: - | G194: 12 | H194: 5 | I194: Known | J194: EN-11 | K194: What was advised, and when, stops being reconstructible only from memory | L194: Turns are append-only and timestamped | M194: B | N194: tested | O194: nm/core/audit.py::TurnHistory - append-only by the ABSENCE of any update or delete method, not by a flag somebody can pass force=True to. TurnRecord holds counts and identifiers and never content, because history is un-erasable and anything it held would survive a deletion meant to be complete (EN-06). The edge check compares the PREFIX, not the length: a history that grew by one while an earlier entry changed is what a length check misses. | P194: nm/tests/a_logic/test_phase6_enterprise.py::test_turn_history_has_no_update_and_no_delete, ::test_history_appends_and_never_rewrites, ::test_a_turn_record_holds_no_content_it_could_never_erase (ran 2026-08-28) | Q194: 2026-08-28
A195: EN-14 | B195: Phase 6 - Enterprise | C195: EP-27 | D195: SLOs and an error budget | E195: Enterprise | F195: D2B | G195: 10 | H195: 5 | I195: Known | J195: F-08 | K195: Reliability becomes a number rather than a feeling | L195: Availability and latency objectives defined and measured | M195: B | N195: built | O195: nm/obs/slo.py::OBJECTIVES - four objectives, each naming the decision its breach would change, so one that changes nothing cannot be declared. Every target is a PLACEHOLDER and unmeasured() reports all four, because nothing in nm/ is served and a target with no data behind it is a guess that will be defended as a commitment. NOT DONE: the 'and measured' half of the acceptance, which needs production traffic. | Q195: 2026-08-28
A196: EN-15 | B196: Phase 6 - Enterprise | C196: EP-27 | D196: Degradation modes: an adapter failure fails the need, not the turn | E196: Enterprise | F196: P5 | G196: 10.3 | H196: 5 | I196: Known | J196: V-07 | K196: An index outage stops taking the product down | L196: The gap becomes visible; the turn completes | M196: B | N196: tested | O196: nm/core/degrade.py - an adapter failure fails the NEED and the turn completes. The half that gets skipped is the second one, so a DegradedNeed must state a consequence and TurnOutcome.must_be_surfaced is checked against what the answer actually said. is_a_coverage_finding() always returns False and exists to fail at the call site: G7 distinguishes not-held from held-but-not-retrieved, and an outage is neither. | P196: nm/tests/a_logic/test_phase6_enterprise.py::test_an_adapter_failure_fails_the_need_not_the_turn, ::test_a_degraded_need_that_never_reached_the_answer_is_caught, ::test_an_outage_is_never_a_coverage_finding (ran 2026-08-28) | Q196: 2026-08-28
A197: EN-16 | B197: Phase 6 - Enterprise | C197: EP-27 | D197: Observability, dashboards and alerting | E197: Enterprise | F197: E6 | G197: 10.2 | H197: 8 | I197: Known | J197: F-08 | K197: Regressions get noticed without someone looking | L197: Alerts on SLO burn, violation rate and cost per turn | M197: B | N197: built | O197: nm/obs/slo.py::evaluate - alerts fire on breach and on a CONSUMED ERROR BUDGET, never on one event: a single slow turn is not a signal, and paging on one is how an alert becomes something people mute. An Alert must name its runbook. burn_threshold defaults to 1.0 because no observation exists to set a lower one from. NOT DONE: dashboards and alert delivery, which need a deployment. | Q197: 2026-08-28
A198: EN-17 | B198: Phase 6 - Enterprise | C198: EP-27 | D198: Backup and restore for matter store and corpus | E198: Enterprise | F198: - | G198: 10.4 | H198: 8 | I198: Known | J198: EN-05 | K198: Data loss stops being terminal | L198: Restore exercised, not merely configured | M198: B | N198: decided | O198: NOT STARTED. Backup and restore need a deployed store; the acceptance is 'restore exercised, not merely configured', which cannot be satisfied against infrastructure that does not exist. | Q198: 2026-08-28
A199: EN-18 | B199: Phase 6 - Enterprise | C199: EP-27 | D199: Load and capacity testing | E199: Enterprise | F199: - | G199: 10 | H199: 8 | I199: Unknown until instrumented | J199: EN-14 | K199: Concurrency limits become known before a customer finds them | L199: Capacity documented with the measurement behind it | M199: C | N199: decided | O199: NOT STARTED. Load and capacity testing need a running system. The acceptance asks for capacity documented with the measurement behind it, and there is nothing to measure. | Q199: 2026-08-28
A200: EN-19 | B200: Phase 6 - Enterprise | C200: EP-28 | D200: Per-turn and per-matter cost attribution | E200: Enterprise | F200: D2B | G200: 10.6 | H200: 5 | I200: Known | J200: F-08 | K200: Unit economics become knowable | L200: Cost attributable to a turn and to a matter | M200: B | N200: tested | O200: nm/obs/cost.py::cost_of_turn - cost is DERIVED from TurnMetrics.model_mix, which the turn already records for its own reasons, so no second counter can drift out of step with what the turn did. A model with no rate is listed as UNPRICED rather than treated as free: a gap that reports as zero is discovered on an invoice. The rate table is a required argument with no default, because provider prices change without notice. | P200: nm/tests/a_logic/test_phase6_enterprise.py::test_cost_is_derived_from_the_turns_own_recorded_model_mix, ::test_a_model_with_no_rate_is_unpriced_never_free, ::test_a_rate_must_carry_its_currency_and_the_date_it_was_quoted (ran 2026-08-28) | Q200: 2026-08-28
A201: EN-20 | B201: Phase 6 - Enterprise | C201: EP-28 | D201: Budget guards and quota | E201: Enterprise | F201: D2B | G201: 10.6 | H201: 5 | I201: Known | J201: EN-19 | K201: A runaway file stops being a surprise invoice | L201: Configurable limits with visible warnings | M201: B | N201: tested | O201: nm/obs/cost.py::Budget - a configurable limit with a warning threshold that is a REQUIRED argument, because a threshold nobody chose either never fires or fires constantly. Exceeding a budget does not stop work unless blocks=True was chosen deliberately: D2 priority 1 says a missing answer is worse than a dear one, and stopping work on a privileged matter is a decision someone takes. | P201: nm/tests/a_logic/test_phase6_enterprise.py::test_a_budget_warns_before_it_stops_and_the_warning_must_be_shown, ::test_exceeding_a_budget_does_not_stop_work_unless_that_was_chosen (ran 2026-08-28) | Q201: 2026-08-28
A202: EN-21 | B202: Phase 6 - Enterprise | C202: EP-28 | D202: Cost regression gate in CI | E202: Eval | F202: D2B | G202: 10.6 | H202: 5 | I202: Known | J202: EN-19,F-07 | K202: Added cost has to show what it bought | L202: A release regressing cost without a measured quality gain fails the gate | M202: C | N202: built | O202: nm/obs/cost.py - check_regression compared `quality_after > quality_before` and called that an improvement, which is true of an accuracy and false of an error rate, a latency, a refusal count and a cost. Measured: a release whose hallucination rate fell 0.20 -> 0.10 FAILED the gate and one whose rate rose 0.10 -> 0.20 PASSED it. Not a near miss - the answer inverted. Direction is now a required argument with no default, because a default here is a guess about somebody else's number and it is wrong silently and in the direction that ships the regression. Held at `built`: the class-C evidence, an actual release comparison over the corpus, has never been produced. | Q202: 2026-08-28
A203: EN-22 | B203: Phase 6 - Enterprise | C203: EP-29 | D203: Staging environment with a corpus snapshot | E203: Enterprise | F203: - | G203: 9 | H203: 8 | I203: Known | J203: I-07 | K203: Changes can be verified before they reach an advocate | L203: Staging mirrors production corpus version | M203: C | N203: decided | O203: NOT STARTED. A staging environment mirroring the production corpus version needs both environments to exist. | Q203: 2026-08-28
A204: EN-23 | B204: Phase 6 - Enterprise | C204: EP-29 | D204: Canary release and rollback | E204: Enterprise | F204: - | G204: 9 | H204: 5 | I204: Known | J204: EN-22 | K204: A bad release stops being a full-population event | L204: Rollback exercised, not merely documented | M204: B | N204: decided | O204: NOT STARTED. The acceptance is 'rollback exercised, not merely documented', which needs a deployment to roll back. | Q204: 2026-08-28
A205: EN-24 | B205: Phase 6 - Enterprise | C205: EP-29 | D205: Golden and e2e runs behind an explicit approval gate | E205: Eval | F205: E5 | G205: 11 | H205: 3 | I205: Known | J205: F-06 | K205: Expensive runs stop happening by accident | L205: A run cannot start without recorded approval and a stated cost | M205: D | N205: built | O205: DOWNGRADED from tested. nm/obs/approval.py had a real defect and it is fixed: Run.start kept the ORIGINAL live approval on the Run and returned the consumed copy separately, so run.approval was live and started a second run in one line - the re-run E5 names, reachable through the object that exists precisely to record that the first one happened. The run now holds the spent approval and refuses to exist holding anything else. The status is the honest part: this story is Class D, and its class-D evidence - that the gate actually stops a real expensive run - has never been produced, because no golden or e2e run has ever been started through it. The deterministic half is tested; a class-D story resting on class-A evidence is `built`. | Q205: 2026-08-28
A206: EN-25 | B206: Phase 6 - Enterprise | C206: EP-29 | D206: Release checklist tied to E7 statuses | E206: Enterprise | F206: E7 | G206: 12 | H206: 3 | I206: Known | J206: F-09 | K206: Shipping something still marked decided becomes visible | L206: No release includes a decision below tested | M206: A | N206: tested | O206: nm/tools/release.py - the gate passed over nothing. statuses_from_plan dropped every row whose status it could not parse and returned a bare mapping, so a plan that failed to open produced an EMPTY map, no story below the bar, and the report `release: all 0 stories are at least tested`. The check ran, over nothing, and said yes. Coverage now travels with the result (PlanStatuses carries what it could not read), an unreadable status BLOCKS rather than disappearing - a skipped row is a row reported as fine, which is the legacy verifier counting a skipped check as a pass, in the gate written to avoid it - and may_release requires considered > 0. | P206: nm/tests/a_logic/test_phase6_enterprise.py::test_a_release_check_over_nothing_is_not_a_passing_check, ::test_a_status_nobody_can_read_blocks_rather_than_disappearing (ran 2026-08-28) | Q206: 2026-08-28
A207: EN-26 | B207: Phase 6 - Enterprise | C207: EP-30 | D207: Correct the product copy: senior counsel, not a junior | E207: Product | F207: D1 | G207: 2 | H207: 2 | I207: Known | K207: The product stops describing itself as the thing it was redesigned away from | L207: No surface describes NM as working the file the way a junior would | M207: A | N207: built | O207: nm/tools/copycheck.py - finds FOUR places that describe NM as a junior: prompts/intake.py 'a senior Indian advocate's intake clerk' (x2) and prompts/research.py 'a legal researcher synthesising retrieval output'. NOT DONE: the correction itself. Those are legacy prompts, and the legacy system is deliberately kept runnable because the Baseline measurements only mean anything while the measured system works - changing a persona prompt changes its behaviour and invalidates the baseline. That is a decision for the user, not a silent edit. | Q207: 2026-08-28
A208: EN-27 | B208: Phase 6 - Enterprise | C208: EP-30 | D208: Onboarding and in-product guidance | E208: Product | F208: - | G208: 4 | H208: 8 | I208: Known | J208: AN-07 | K208: A new advocate gets to a first useful answer unaided | L208: First-session completion measured | M208: D | N208: decided | O208: NOT STARTED. Onboarding is a product surface with a Class D acceptance ('first-session completion measured'); there is no served product to onboard into. | Q208: 2026-08-28
A209: EN-28 | B209: Phase 6 - Enterprise | C209: EP-30 | D209: Support runbooks | E209: Product | F209: - | G209: 10 | H209: 5 | I209: Known | J209: EN-16 | K209: A failure gets diagnosed without the author present | L209: Runbook per alert, exercised once | M209: B | N209: built | O209: nm/obs/compliance.py::RUNBOOKS - one runbook per alert nm.obs.slo can raise, checked against OBJECTIVES rather than a list kept alongside, so adding an objective without its runbook fails. NOT DONE: the acceptance says 'exercised once' and none has been. exercised_on is empty for all four rather than backdated - none of these alerts can fire against a system with no traffic. | Q209: 2026-08-28
A210: EN-29 | B210: Phase 6 - Enterprise | C210: EP-30 | D210: Pricing and packaging decision | E210: Product | F210: - | G210: 2 | H210: 5 | I210: Unknown until instrumented | J210: EN-19 | K210: Unit economics become a business decision rather than a guess | L210: Price per seat or matter set against measured cost | M210: D | N210: decided | O210: NOT STARTED, and not mine to start. Pricing per seat or matter against measured cost is a commercial decision; the cost side now has machinery (EN-19) but no measured figure, and the price side is the practice's call. | Q210: 2026-08-28
A211: IN-01 | B211: Phase 7 - Integration | C211: EP-31 | D211: EvidencePort and the EvidenceNeed contract | E211: Core | F211: G2,G9 | G211: 8.2 | H211: 5 | I211: Known | J211: V-01 | K211: The core can ask for law without holding an index | L211: A need carries structured matter state, never a bare string | M211: A | N211: tested | O211: nm/core/needs.py - EvidenceNeed carries a structured MatterState, not a text string, so search cannot run before resolution (G2/ADR-1). The governing date is a required field with no default (G1): 'today' is what answers a 2019 question with 2026 law. EvidencePort returns Findings, never chunks (G9). Lives in core rather than ports because nm.ports may import only nm.ports and this interface traffics in Finding - a stdlib mirror in ports would be a second representation of the retrieval contract, free to drift from the one verification enforces. | P211: nm/tests/a_logic/test_phase7_turn.py::test_a_need_carries_the_matter_not_just_a_question, ::test_the_governing_date_cannot_be_omitted (ran 2026-08-28) | Q211: 2026-08-28
A212: IN-02 | B212: Phase 7 - Integration | C212: EP-31 | D212: ModelPort, reachable only through a declared step | E212: Core | F212: D2B | G212: 10.5,10.6 | H212: 5 | I212: Known | J212: F-11,F-12 | K212: Every model call has an owner and a recorded cost | L212: A call without a registered step is refused | M212: A | N212: tested | O212: nm/core/gateway.py - the only door to a model call, and it refuses a Step the registry does not hold. The check is IDENTITY (REGISTRY.get(id) is step), not membership: an id check passes for a locally built Step reusing a registered id with different prompt text, which is the duplicate-prompt failure arriving through the call site instead of a second module. Every call records itself into TurnMetrics, so model_mix is derivable without instrumentation scattered through the code (D2B). | P212: nm/tests/a_logic/test_phase7_turn.py::test_a_model_call_from_an_undeclared_step_is_refused, ::test_a_second_step_object_with_a_registered_id_is_refused, ::test_a_model_call_records_itself_in_the_turns_metrics (ran 2026-08-28) | Q212: 2026-08-28
A213: IN-03 | B213: Phase 7 - Integration | C213: EP-31 | D213: MatterStore port and an in-process implementation | E213: Adapter | F213: D15 | G213: 5 | H213: 5 | I213: Known | J213: EN-02 | K213: A turn can persist and resume | L213: Reads and writes are access-checked per advocate | M213: B | N213: tested | O213: nm/adapters/inprocess.py::InMemoryMatterStore - a real implementation of the MatterStore port that genuinely enforces the per-advocate access check, because a store whose isolation is a stub trains every caller to assume reads succeed. Reports its protection as UNAVAILABLE rather than unprotected: an in-memory store has no key and no provider configured, which is the state the legacy crypto layer reported as success (B-74). | P213: nm/tests/a_logic/test_phase7_turn.py::test_the_in_process_store_really_denies_access, ::test_an_in_process_store_reports_its_protection_as_unavailable (ran 2026-08-28) | Q213: 2026-08-28
A214: IN-04 | B214: Phase 7 - Integration | C214: EP-31 | D214: The turn orchestrator: architecture 8 in dependency order | E214: Core | F214: Q1,Q10,S3 | G214: 8,8.1 | H214: 13 | I214: Unknown until instrumented | J214: IN-01,IN-02,GQ-02,AN-02 | K214: The components become a product | L214: One message and one document produce an answer, a board and a summary | M214: B | N214: tested | O214: nm/core/turn.py::run_turn - architecture 8 in dependency order: infer the mode, integrate facts, cascade corrections, compute gates, run the bounded evidence loop, build the gap queue across the file, phrase the questions it owes, re-orient on a real delta, assemble. Found one defect immediately (B-84): the no-change condition ignored the elements and findings the turn produced, so a turn with a recommendation and retrieved law was declared quiet and its answer replaced by the S7 line. NOT DONE: the analysis stages - theory, proof, adversarial, salvage, selection - are model-driven, each needs its own declared step, and the orchestrator carries thread state through and leaves them to the caller. | P214: nm/tests/a_logic/test_phase7_turn.py::test_a_turn_runs_end_to_end_and_produces_an_answer, ::test_the_mode_is_inferred_from_the_turns_own_state, ::test_every_question_the_turn_asks_traces_to_a_blocking_gate (ran 2026-08-28) | Q214: 2026-08-28
A215: IN-05 | B215: Phase 7 - Integration | C215: EP-31 | D215: The evidence loop is bounded and the bound is stated | E215: Core | F215: D2B | G215: 8.2 | H215: 3 | I215: Known | J215: IN-04 | K215: A turn stays measurable | L215: The loop terminates and reports the round it stopped on | M215: A | N215: tested | O215: nm/core/turn.py - `rounds` is a required argument with no default, because the number of evidence rounds a matter deserves is a property of the matter and a default here would be an unmeasured constant deciding how hard the system tries. EvidenceRounds reports whether the loop was EXHAUSTED, so a turn that stopped at the bound is visible rather than merely shorter. A round that answered nothing breaks rather than burning the budget to no effect. | P215: nm/tests/a_logic/test_phase7_turn.py::test_the_evidence_loop_terminates_and_says_where_it_stopped, ::test_a_zero_round_budget_reports_exhaustion_rather_than_silence, ::test_the_round_budget_has_no_default (ran 2026-08-28) | Q215: 2026-08-28
A216: IN-06 | B216: Phase 7 - Integration | C216: EP-31 | D216: A blocking gate short-circuits its thread and pays for nothing | E216: Core | F216: Q1,D8 | G216: 8.1 | H216: 5 | I216: Known | J216: IN-04 | K216: Correctness and cost from one mechanism | L216: No derivation and no evidence need is produced below an open blocking gate | M216: B | N216: tested | O216: nm/core/turn.py::_needs_for - a blocked thread emits NO evidence need. One early return serves both purposes: nothing wrong is generated below an open gate (correctness) and nothing is paid for (cost), which is why they cannot drift apart. Asserted against a spy adapter that records what it was asked, so 'a blocked thread asked for nothing' is measured rather than assumed. | P216: nm/tests/a_logic/test_phase7_turn.py::test_a_blocked_thread_emits_no_evidence_need_and_pays_for_nothing, ::test_an_unblocked_thread_does_ask (ran 2026-08-28) | Q216: 2026-08-28
A217: IN-07 | B217: Phase 7 - Integration | C217: EP-31 | D217: Deterministic adapters so a turn runs with no network | E217: Adapter | F217: E1 | G217: 5 | H217: 5 | I217: Known | J217: IN-01,IN-02 | K217: The turn is testable at commit cadence | L217: A full turn runs inside the class-A guards | M217: B | N217: tested | O217: nm/adapters/inprocess.py - real implementations of the real ports with the non-determinism removed rather than the interface faked, so a full turn runs inside the class-A guards (no sockets, no corpus, no LLM) at commit cadence. ScriptedModel REFUSES a step it has no answer for rather than returning an empty string that would fail in the consumer and point the traceback at the wrong module. These prove the components compose and nothing else - not that retrieval works, not that a turn is any good. | P217: nm/tests/a_logic/test_phase7_turn.py::test_a_turn_runs_end_to_end_and_produces_an_answer (runs under the class-A network and legacy-import guards) (ran 2026-08-28) | Q217: 2026-08-28
A218: IN-08 | B218: Phase 7 - Integration | C218: EP-31 | D218: One real turn, asserted end to end with its metrics | E218: Eval | F218: E3,E6 | G218: 8,12 | H218: 8 | I218: Unknown until instrumented | J218: IN-04,IN-07 | K218: The first thing that can be verified live | L218: Every class-B assertion runs against a real turn and its violations are collected | M218: B | N218: tested | O218: nm/edge/session.py::serve - the Phase 6 class-B invariants now have a production caller, which was the review's F8 and the reason five of the seven P1 defects survived their own tests. Always asserted: the access record (counted across the call), the diagnostics line, the provenance of every statement, the append-only history. Asserted when their input exists: cost attribution, budget state, degraded needs - a turn with no rate table has no cost to attribute, and asserting over an absent input is the check that passes because nothing was there. Never here and said so rather than quietly counted as wired: assert_erasure_is_complete, because erasure is not a turn. serve also refuses a summary belonging to another matter, and requires a session and the facts the answer walks back to. | P218: nm/tests/a_logic/test_phase7_turn.py::test_a_served_turn_runs_the_phase_6_invariants_and_not_only_the_phase_4_ones, ::test_a_turn_served_for_one_matter_cannot_use_another_matters_summary (ran 2026-08-28) | Q218: 2026-08-28

Sheet Epics
A1: Epic | B1: Phase | C1: Name | D1: Why it is here | E1: Stories | F1: Points | G1: Unknowns
A2: EP-01 | B2: Phase 0 - Foundation | C2: Engineering foundation and the eval harness | D2: The test cadence is a design input; nothing later is enforceable without it | E2: =COUNTIF(Backlog!$C$2:$C$218,$A2) | F2: =SUMIF(Backlog!$C$2:$C$218,$A2,Backlog!$H$2:$H$218) | G2: =COUNTIFS(Backlog!$C$2:$C$218,$A2,Backlog!$I$2:$I$218,"Unknown until instrumented")
A3: EP-02 | B3: Phase 0 - Foundation | C3: Data model and derivation graph | D3: A schema that cannot express a rule makes that rule unimplementable | E3: =COUNTIF(Backlog!$C$2:$C$218,$A3) | F3: =SUMIF(Backlog!$C$2:$C$218,$A3,Backlog!$H$2:$H$218) | G3: =COUNTIFS(Backlog!$C$2:$C$218,$A3,Backlog!$I$2:$I$218,"Unknown until instrumented")
A4: EP-03 | B4: Phase 1 - Knowledge | C4: Legal graph | D4: Resolution needs structure to resolve against | E4: =COUNTIF(Backlog!$C$2:$C$218,$A4) | F4: =SUMIF(Backlog!$C$2:$C$218,$A4,Backlog!$H$2:$H$218) | G4: =COUNTIFS(Backlog!$C$2:$C$218,$A4,Backlog!$I$2:$I$218,"Unknown until instrumented")
A5: EP-04 | B5: Phase 1 - Knowledge | C5: Corpus manifest | D5: Until it exists, an honest refusal and a retrieval defect are indistinguishable | E5: =COUNTIF(Backlog!$C$2:$C$218,$A5) | F5: =SUMIF(Backlog!$C$2:$C$218,$A5,Backlog!$H$2:$H$218) | G5: =COUNTIFS(Backlog!$C$2:$C$218,$A5,Backlog!$I$2:$I$218,"Unknown until instrumented")
A6: EP-05 | B6: Phase 1 - Knowledge | C6: Ingestion | D6: Including the binding court the corpus currently lacks entirely | E6: =COUNTIF(Backlog!$C$2:$C$218,$A6) | F6: =SUMIF(Backlog!$C$2:$C$218,$A6,Backlog!$H$2:$H$218) | G6: =COUNTIFS(Backlog!$C$2:$C$218,$A6,Backlog!$I$2:$I$218,"Unknown until instrumented")
A7: EP-06 | B7: Phase 1 - Knowledge | C7: Indices and summaries | D7: Section level is both the missing retrieval granularity and the missing summary granularity | E7: =COUNTIF(Backlog!$C$2:$C$218,$A7) | F7: =SUMIF(Backlog!$C$2:$C$218,$A7,Backlog!$H$2:$H$218) | G7: =COUNTIFS(Backlog!$C$2:$C$218,$A7,Backlog!$I$2:$I$218,"Unknown until instrumented")
A8: EP-07 | B8: Phase 1 - Knowledge | C8: Citation graph and treatment | D8: Authority lines, and is-this-still-good-law | E8: =COUNTIF(Backlog!$C$2:$C$218,$A8) | F8: =SUMIF(Backlog!$C$2:$C$218,$A8,Backlog!$H$2:$H$218) | G8: =COUNTIFS(Backlog!$C$2:$C$218,$A8,Backlog!$I$2:$I$218,"Unknown until instrumented")
A9: EP-08 | B9: Phase 2 - Evidence | C9: Resolution | D9: The query is the matter, not a sentence | E9: =COUNTIF(Backlog!$C$2:$C$218,$A9) | F9: =SUMIF(Backlog!$C$2:$C$218,$A9,Backlog!$H$2:$H$218) | G9: =COUNTIFS(Backlog!$C$2:$C$218,$A9,Backlog!$I$2:$I$218,"Unknown until instrumented")
A10: EP-09 | B10: Phase 2 - Evidence | C10: Search | D10: Scoped by law; similarity may only reorder | E10: =COUNTIF(Backlog!$C$2:$C$218,$A10) | F10: =SUMIF(Backlog!$C$2:$C$218,$A10,Backlog!$H$2:$H$218) | G10: =COUNTIFS(Backlog!$C$2:$C$218,$A10,Backlog!$I$2:$I$218,"Unknown until instrumented")
A11: EP-10 | B11: Phase 2 - Evidence | C11: Verification | D11: Where grounding stops being an aspiration and becomes a gate | E11: =COUNTIF(Backlog!$C$2:$C$218,$A11) | F11: =SUMIF(Backlog!$C$2:$C$218,$A11,Backlog!$H$2:$H$218) | G11: =COUNTIFS(Backlog!$C$2:$C$218,$A11,Backlog!$I$2:$I$218,"Unknown until instrumented")
A12: EP-11 | B12: Phase 3 - Analysis | C12: Threads and identity | D12: A wrong merge inverts the advice invisibly | E12: =COUNTIF(Backlog!$C$2:$C$218,$A12) | F12: =SUMIF(Backlog!$C$2:$C$218,$A12,Backlog!$H$2:$H$218) | G12: =COUNTIFS(Backlog!$C$2:$C$218,$A12,Backlog!$I$2:$I$218,"Unknown until instrumented")
A13: EP-12 | B13: Phase 3 - Analysis | C13: Facts, provenance and the correction cascade | D13: A corrected fact must not leave stale conclusions beneath it | E13: =COUNTIF(Backlog!$C$2:$C$218,$A13) | F13: =SUMIF(Backlog!$C$2:$C$218,$A13,Backlog!$H$2:$H$218) | G13: =COUNTIFS(Backlog!$C$2:$C$218,$A13,Backlog!$I$2:$I$218,"Unknown until instrumented")
... A32: EP-31 | B32: Phase 7 - Integration | C32: The turn: wiring the components into a product | D32: Every component is tested and nothing has ever run; five P1 defects survived every gate | E32: =COUNTIF(Backlog!$C$2:$C$218,$A32) | F32: =SUMIF(Backlog!$C$2:$C$218,$A32,Backlog!$H$2:$H$218) | G32: =COUNTIFS(Backlog!$C$2:$C$218,$A32,Backlog!$I$2:$I$218,"Unknown until instrumented")

Sheet Dependencies
A1: Story | B1: Blocked by | C1: Story title | D1: Blocker title
A2: F-02 | B2: F-01 | C2: CI rule: core may import only core and ports; violation fails the build | D2: Split the repo into core / ports / adapters / knowledge / edge / obs
A3: F-03 | B3: F-01 | C3: Class-A test runner: no corpus, no LLM, whole suite under 10s | D3: Split the repo into core / ports / adapters / knowledge / edge / obs
A4: F-04 | B4: F-01 | C4: Class-B runtime assertion framework writing to TurnMetrics.violations | D4: Split the repo into core / ports / adapters / knowledge / edge / obs
A5: F-04 | B5: D-01 | C5: Class-B runtime assertion framework writing to TurnMetrics.violations | D5: Core entity definitions from the information view
A6: F-05 | B6: F-01 | C6: Class-C corpus test runner | D6: Split the repo into core / ports / adapters / knowledge / edge / obs
A7: F-06 | B7: F-05 | C7: Class-D rubric harness using a judge model distinct from the answering model | D7: Class-C corpus test runner
A8: F-07 | B8: F-08 | C8: Baseline record, seeded with the measurements already taken | D8: Turn metrics: latency, call count, tokens, model mix, per-stage timings
A9: F-08 | B9: F-01 | C9: Turn metrics: latency, call count, tokens, model mix, per-stage timings | D9: Split the repo into core / ports / adapters / knowledge / edge / obs
A10: F-09 | B10: F-03 | C10: Status tracking: decided / built / tested / verified live | D10: Class-A test runner: no corpus, no LLM, whole suite under 10s
A11: F-10 | B11: F-01 | C11: Error policy: programming errors caught separately and logged at ERROR with traceback | D11: Split the repo into core / ports / adapters / knowledge / edge / obs
A12: F-11 | B12: F-01 | C12: Prompt ownership registry: exactly one owner per step, no duplicated text | D12: Split the repo into core / ports / adapters / knowledge / edge / obs
... A268: EN-29 | B268: EN-19 | C268: Pricing and packaging decision | D268: Per-turn and per-matter cost attribution

Sheet PRD Coverage
A1: # | B1: Date | C1: PRD decision | D1: Section | E1: Discharged by | F1: Status
A2: 1 | B2: 2026-08-26 | C2: Advocate-only product; no direct-to-client mode | D2: D1 | E2: TH-02,AD-04,EN-26 | F2: built
A3: 2 | B3: 2026-08-26 | C3: Corpus stays Telangana + Union of India; gaps disclosed, not filled from memory | D3: D3A | E3: I-03,M-02 | F3: decided
A4: 3 | B4: 2026-08-26 | C4: Launch areas: land & revenue, matrimonial, bail | D4: D4 | E4: M-02 | F4: tested
A5: 4 | B5: 2026-08-26 | C5: Order of work adopted (Part I §1); posture is step 1 | D5: D7 | E5: GQ-01 | F5: tested
A6: 5 | B6: 2026-08-26 | C6: Posture is per matter, not per client; unknown blocks directive advice | D6: D8 | E6: PO-01,PO-02,PO-03,PO-04,PO-05 | F6: tested
A7: 6 | B7: 2026-08-26 | C7: Posture shown as a cause-title table, second element on the matter board | D7: D8 | E7: PO-01,PO-02,PO-03,PO-04,PO-05 | F7: tested
A8: 7 | B8: 2026-08-26 | C8: Left pane default a third of the window, draggable to 40% | D8: D13A | E8: AN-01,AN-02,AN-03,AN-04,AN-05,AN-06,AN-07 | F8: tested
A9: 8 | B9: 2026-08-26 | C9: Enrichment monotonic and evidence-gated; a stated posture is never silently flipped | D9: D8 | E9: PO-01,PO-02,PO-03,PO-04,PO-05 | F9: tested
A10: 9 | B10: 2026-08-26 | C10: No further code changes until a section here is finalised | D10: PROCESS | E10: n/a - working agreement, not a build item | F10: n/a
A11: 10 | B11: 2026-08-26 | C11: NM is senior counsel, not a junior — critical thinker and problem solver; disagrees with the brief, reframes, volunteers, commits to a recommendation, argues the other side, names exposure | D11: D1 | E11: TH-02,AD-04,EN-26 | F11: built
A12: 11 | B12: 2026-08-26 | C12: Expertise is in reasoning and judgement, never in recalling law from memory; the corpus-grounding discipline is unchanged | D12: D5 | E12: V-06,V-07,AN-11,M-04 | F12: tested
A13: 12 | B13: 2026-08-26 | C13: Decisiveness is a requirement — a survey of options is not advice | D13: D2 | E13: AN-02 | F13: tested
... A187: 186 | B187: 2026-08-27 | C187: CS5: the summary reads as a case note, not a debug dump — identifiers, scores and pipeline state belong in diagnostics (G8) | D187: D13A | E187: AN-10 | F187: built
A188: 187 | B188: 2026-08-28 | C188: D16.1: Professional stance - end-to-end advocate behaviour; detailed implementation audit and improvement recommendation are on the Advocate Behaviour sheet. | D188: D16 | E188: AB-01 (Advocate Behaviour sheet) | F188: built
A189: 188 | B189: 2026-08-28 | C189: D16.2: Competence - end-to-end advocate behaviour; detailed implementation audit and improvement recommendation are on the Advocate Behaviour sheet. | D189: D16 | E189: AB-02 (Advocate Behaviour sheet) | F189: built
A190: 189 | B190: 2026-08-28 | C190: D16.3: Before receiving substance - end-to-end advocate behaviour; detailed implementation audit and improvement recommendation are on the Advocate Behaviour sheet. | D190: D16 | E190: AB-03 (Advocate Behaviour sheet) | F190: decided
A191: 190 | B191: 2026-08-28 | C191: D16.4: Authority and engagement - end-to-end advocate behaviour; detailed implementation audit and improvement recommendation are on the Advocate Behaviour sheet. | D191: D16 | E191: AB-04 (Advocate Behaviour sheet) | F191: decided
A192: 191 | B192: 2026-08-28 | C192: D16.5: First human contact - end-to-end advocate behaviour; detailed implementation audit and improvement recommendation are on the Advocate Behaviour sheet. | D192: D16 | E192: AB-05 (Advocate Behaviour sheet) | F192: built
A193: 192 | B193: 2026-08-28 | C193: D16.6: Emergency triage - end-to-end advocate behaviour; detailed implementation audit and improvement recommendation are on the Advocate Behaviour sheet. | D193: D16 | E193: AB-06 (Advocate Behaviour sheet) | F193: built
A194: 193 | B194: 2026-08-28 | C194: D16.7: Client interview - end-to-end advocate behaviour; detailed implementation audit and improvement recommendation are on the Advocate Behaviour sheet. | D194: D16 | E194: AB-07 (Advocate Behaviour sheet) | F194: built
A195: 194 | B195: 2026-08-28 | C195: D16.8: Objectives and constraints - end-to-end advocate behaviour; detailed implementation audit and improvement recommendation are on the Advocate Behaviour sheet. | D195: D16 | E195: AB-08 (Advocate Behaviour sheet) | F195: built
A196: 195 | B196: 2026-08-28 | C196: D16.9: Parties and posture - end-to-end advocate behaviour; detailed implementation audit and improvement recommendation are on the Advocate Behaviour sheet. | D196: D16 | E196: AB-09 (Advocate Behaviour sheet) | F196: tested
A197: 196 | B197: 2026-08-28 | C197: D16.10: Fact model - end-to-end advocate behaviour; detailed implementation audit and improvement recommendation are on the Advocate Behaviour sheet. | D197: D16 | E197: AB-10 (Advocate Behaviour sheet) | F197: tested
A198: 197 | B198: 2026-08-28 | C198: D16.11: Evidence and preservation - end-to-end advocate behaviour; detailed implementation audit and improvement recommendation are on the Advocate Behaviour sheet. | D198: D16 | E198: AB-11 (Advocate Behaviour sheet) | F198: built
A199: 198 | B199: 2026-08-28 | C199: D16.12: Threshold legal map - end-to-end advocate behaviour; detailed implementation audit and improvement recommendation are on the Advocate Behaviour sheet. | D199: D16 | E199: AB-12 (Advocate Behaviour sheet) | F199: built
... A215: 214 | B215: 2026-08-28 | C215: D16.28: After each event and at closure - end-to-end advocate behaviour; detailed implementation audit and improvement recommendation are on the Advocate Behaviour sheet. | D215: D16 | E215: AB-28 (Advocate Behaviour sheet) | F215: built

Sheet Bugs
A1: ID | B1: Found by | C1: Where | D1: Defect | E1: Detail | F1: Sev | G1: Pts | H1: Status | I1: Fix / story | J1: Evidence
A2: B-01 | B2: live session | C2: agents/legal_analysis | D2: Stale call site after a rename emptied every charge map | E2: A rename left `_drop_non_issues` referenced but undefined. It raised NameError on every matter for weeks; a broad `except Exception` logged it as a model failure, so the symptom looked like flakiness. | F2: P1 | G2: 3 | H2: fixed | I2: legacy fix; rule carried into F-10 + exceptcheck | J2: resolve_charges returned 0 charges on a matter with 9 merits issues
A3: B-02 | B3: live session | C3: agents/orchestrator | D3: Every advising turn crashed on an unbound local | E3: The AUTHORITATIVE CHARGES block was indented into the `steps` branch instead of the `charges` branch, so `_cite_how` was used before assignment on every advising turn. | F3: P1 | G3: 2 | H3: fixed | I3: legacy fix; swept by pylint E0601/E0606 in CI | J3: UnboundLocalError on every advising turn; 40/40 offline tests green throughout
A4: B-03 | B4: live session | C4: agents/legal_analysis | D4: An invented track vocabulary emptied the charge map | E4: The charge resolver returned tracks {'civil': 2, 'revenue': 1} — subject words, not procedural tracks. They passed unvalidated and merits_only dropped every one. | F4: P1 | G4: 3 | H4: fixed | I4: legacy fix; generalised as F5 (closed vocabulary validated at every entry) | J4: {'civil','revenue'} -> 0 charges on a 9-issue matter
A5: B-04 | B5: retrieval probe | C5: retrieval/retriever | D5: An unlisted atom type scored below every listed one | E5: `table.get(kind, 0.0)` made any atom type absent from the priors table score worse than all present ones, and the bonus was an absolute constant larger than the whole RRF range (best fused score 2/61). | F5: P1 | G5: 5 | H5: fixed | I5: legacy fix; generalised as R4 (absent key is neutral; scale to the spread) | J5: Limitation Art. 59: rank 1 -> 53 of 60; after the fix rank 1, and rank 2 with its own entry stripped
A6: B-05 | B6: index audit | C6: legal_database | D6: A stale BM25 index served old results silently | E6: The native BM25 index held 411,797 documents against the JSON's 414,710 and had been stale since 11 July, answering every query without complaint. | F6: P1 | G6: 2 | H6: fixed | I6: legacy fix; generalised as G21 / I-08 (stale artefact refused) | J6: 411,797 vs 414,710 documents
A7: B-06 | B7: live session | C7: agents/posture | D7: Posture inverted: advice given to the wrong side | E7: NM told a client who had drawn a dishonoured cheque to file the s.138 complaint against himself, and told an employer who had dismissed a workman that he could claim reinstatement. Every citation was real and apposite. | F7: P1 | G7: 8 | H7: fixed | I7: legacy fix (agents/posture.py); rebuilt as PO-01..PO-05 | J7: 5-dispute live file; 2 of 5 threads inverted. Legacy fix NOT verified live
A8: B-07 | B8: measurement | C8: agents/legal_analysis | D8: Classification deleted 20.1% of every issue ever spotted | E8: The pre-routing filters discarded 641 of 3,192 issue labels across every stored matter, led by limitation (122), bail (86) and forum/jurisdiction (58) — the three an advocate can least afford to lose. | F8: P1 | G8: 5 | H8: fixed | I8: legacy fix (route, never delete); rebuilt as F2 / IS-04 | J8: 641 of 3,192 labels discarded
A9: B-08 | B9: ingest audit | C9: legal_database | D9: A judgment was ingested twice | E9: Vidhyadhar v Manikrao was ingested as a new case while already present under SC_1999_VIDHYADHAR_VS_MANIKRAO_ANR. | F9: P3 | G9: 1 | H9: fixed | I9: removed; prevented by I-06 (idempotent ingest) | J9: 5th false retrieval gap traced to a duplicate
A10: B-09 | B10: live session | C10: agents/orchestrator | D10: A date given in the brief was never applied to limitation | E10: NM was told the debtor acknowledged the debt in writing on 12 June 2024, repeated it back, and still concluded the claim was time-barred counting three years from the March 2023 invoices. | F10: P1 | G10: 8 | H10: answered | I10: LM-04 / coverage is set equality with the chronology | J10: test_coverage_is_l5_as_a_set_equality_check - every chronology fact appears in coverage with an effect or an exclusion, so a date the brief gave cannot be silently unused
A11: B-10 | B11: code audit | C11: agents/* | D11: A prompt change lands in only one of two prompt systems | E11: The consult path uses _CONSULT_PROMPT; the structured-intake path builds its own _narrow_prompt and never touches it. A change described as global applies to half the product. | F11: P1 | G11: 5 | H11: answered | I11: F-11 / a prompt has exactly one owner | J11: test_a_prompt_has_exactly_one_owner - no prompt string appears in two modules, so a change cannot land in half the product. The legacy split between _CONSULT_PROMPT and intake_engine._narrow_prompt is unchanged and stays that way
A12: B-11 | B12: code audit | C12: agents/orchestrator | D12: Andhra Pradesh authority is weighted without regard to date | E12: _court_weight gives AP a flat rung, so a 2015 AP judgment (binding on Telangana as the predecessor court) and a 2022 one (another state's HC, persuasive only) are treated identically. The year is already in the record. | F12: P2 | G12: 3 | H12: answered | I12: V-04 / binding computed from court, year and forum | J12: nm/knowledge/authority.py - a citation carries binding or persuasive RELATIVE to the forum asking, and the year is part of the computation rather than a tiebreak
A13: B-12 | B13: code audit | C13: agents/orchestrator | D13: A court-ranking rung matches nothing | E13: The `telangana` rung in _court_weight is dead code, because the corpus holds no Telangana judgments at all. | F13: P3 | G13: 1 | H13: open | I13: I-03 (ingest Telangana HC) | J13: 0 Telangana HC judgments in 33,791
... A141: B-140 | B141: Phase 8 second review | C141: nm/tests/a_logic/test_served_api.py | D141: Nothing asserted that a held-back disagreement ever ARRIVES | E141: Found by mutation rather than by review: stopping the disagreements being joined to the draft left the suite green. Held back and then dropped is worse than not held back at all - AB-21's whole value is the difficult thing being said, and it would have gone silently. Both halves are now asserted on the wire: the improper fix cannot leave early, and the doubt does arrive after the screen. | F141: P1 | G141: 1 | H141: fixed | I141: AB-21 / D16.21 | J141: test_a_disagreement_reaches_the_advocate_after_the_screen
A142: B-141 | B142: Phase 8 second review | C142: nm/core/duty.py::Breach | D142: The duty taxonomy has no explicit confidentiality, privilege or conflict outcome | E142: The seven Breach values cover litigation misconduct and say nothing explicit about a recommendation that would breach confidentiality or privilege, or that acts in a conflict. The conflict CHECK is a different control on a different object - it screens the matter, not the advice - so a recommendation that itself creates the problem is unscreened. Recorded rather than fixed: adding categories to a closed list is the easy half, and the hard half is the over-application bound for each, which needs the same both-directions measurement the existing seven had. | F142: P2 | G142: 1 | H142: open | I142: AB-01 / D16.1
A143: B-142 | B143: Phase 8 second review | C143: nm/app/consult.py::DECLARED | D143: Declared competence is a hardcoded constant, not a corpus manifest | E143: Telangana, Union of India and English are declared in the composition root and nothing checks them against what the corpus actually holds. It cannot express a court, a subject, a date range or partial coverage, so with I-03 parked the declaration is broader than the corpus behind it - which makes the competence screen answer confidently about matters it has thin coverage for. Already recorded as this tenet's main gap; restated here as a defect because a declaration nothing verifies is the same class as a rating nobody computes. | F143: P2 | G143: 1 | H143: open | I143: AB-02 / D16.2
A144: B-143 | B144: self-review before claiming AB-03 | C144: nm/app/state.py::Conversations.all | D144: One unreadable matter took the conflict screen down for the whole deployment | E144: Found by attacking my own code rather than by review. The registry is a projection of the stored matters, so a row that will not decode - a partial write, a restore, a rotated key - raised out of all() and every matter on the deployment became unscreenable. The OBVIOUS repair is to skip it, and that is worse than the crash: a matter silently dropped from the registry is a FALSE CLEARANCE, the one outcome this screen exists to prevent. Fixed with a MatterSet that carries the matters and the failures together, so a caller cannot iterate one without seeing the other, and the screening note says the screen was INCOMPLETE and names what it could not cover. | F144: P1 | G144: 1 | H144: fixed | I144: AB-03 / D16.3 | J144: test_one_unreadable_matter_does_not_take_the_screen_down
A145: B-144 | B145: self-review before claiming AB-03 | C145: nm/app/conflicts.py::screening_note | D145: The screening note counted the matter against itself | E145: The registry is a projection and by the time the board renders, THIS matter is one of the stored ones - so the note said 'screened against 1 matter' on the very first brief a deployment ever saw, which is precisely the false reassurance the note exists to prevent. screen() already excludes self; the count now agrees with it. | F145: P2 | G145: 1 | H145: fixed | I145: AB-03 / D16.3 | J145: test_a_shared_party_blocks_the_second_matter_over_http
A146: B-145 | B146: self-review before claiming AB-06 | C146: nm/app/consult.py | D146: An emergency found on one turn vanished on the next | E146: The triage was recomputed from each message and kept nothing, so an arrest found on turn one was gone by turn two - the same defect the competence block had, in the place where it costs most. Conversation now carries every class assessed, not just the live ones, because the question D16.6 asks is not what was found but what was LOOKED AT. | F146: P1 | G146: 1 | H146: fixed | I146: AB-06 / D16.6 | J146: test_an_emergency_found_on_one_turn_still_leads_the_next
A147: B-146 | B147: self-review before claiming AB-06 | C147: nm/core/urgency.py::carry_forward | D147: A later NO silently closed a live emergency, and my first fix had this wrong | E147: The carry-forward rule said 'a class assessed this turn replaces what was held'. That is wrong for the same reason the competence bypass was wrong: THE STEP IS NEVER SILENT. Asked about 'the wall went up in January' it answers 'liberty | NO | does not arise on these facts' - truthful about that message, and it would close an arrest found the turn before. The unit tests passed; a SERVED test caught it. A live urgency is now sticky and only urgency.resolve closes it, with a name. The first sticky guard was then too broad and blocked the resolution itself - caught by the same test - so it tests STANDING rather than is_live, because a resolution is APPLIES-and-closed. | F147: P1 | G147: 1 | H147: fixed | I147: AB-06 / D16.6 | J147: test_a_later_NO_does_not_clear_a_live_urgency
A148: B-147 | B148: self-review before claiming AB-06 | C148: nm/app/triage.py::run | D148: An outage in the urgency step took the whole turn down | E148: The call raised straight out of run(), the consult died, and the advocate got an error page instead of an answer - the one behaviour every other screen in this build avoids. An empty Triage is INCOMPLETE by set equality, so it now reports itself as never having looked rather than as having found nothing, blocks_merits stays true, and the answer says so on its face. | F148: P1 | G148: 1 | H148: fixed | I148: AB-06 / D16.6 | J148: test_a_triage_outage_returns_an_incomplete_screen_rather_than_raising
A149: B-148 | B149: self-review before claiming AB-06 | C149: nm/app/consult.py::_urgent_lead | D149: An action due eight months ago was listed under 'these will not wait' | E149: Which reads as a forecast about something that has already failed to happen. An overdue emergency is worse news than a live one, not stale news: it leads separately, says how many days late it is, and is not filtered out. Same class as the expired-limitation defect, which this build had already fixed once. | F149: P1 | G149: 1 | H149: fixed | I149: AB-06 / D16.6 | J149: test_an_overdue_urgency_is_separated_from_one_still_ahead
A150: B-149 | B150: self-review before claiming AB-06 | C150: nm/core/urgency.py::resolve | D150: There was no way for an advocate to close an emergency out | E150: So a handled arrest would lead every turn forever, and an advocate who learns to skip the top of the answer skips the one that mattered. resolve() takes the person and what they did and keeps the record: 'there was never an emergency here' and 'there was one and it was handled on Tuesday' are different files. | F150: P2 | G150: 1 | H150: fixed | I150: AB-06 / D16.6 | J150: test_silence_is_not_resolution_and_only_a_person_closes_one
A151: B-150 | B151: self-review before claiming AB-04 | C151: nm/core/engagement.py::Engagement | D151: A blank scope line put every step in scope | E151: covers() asks whether a scope phrase appears in the work, and an empty phrase appears in EVERYTHING - so one blank line silently made every step in scope, which is the exact opposite of having a scope. Found by attacking the type rather than by review. Blank scope lines and blank exclusions are both refused now: an empty exclusion excludes everything and the engagement would cover nothing at all. | F151: P1 | G151: 1 | H151: fixed | I151: AB-04 / D16.4 | J151: test_a_blank_scope_line_is_refused_because_it_would_cover_everything
A152: B-151 | B152: self-review before claiming AB-04 | C152: nm/core/engagement.py::reliance | D152: Reliance was a SECOND answer to a question readiness already answered | E152: reliance() knew about the engagement and the conflict check and nothing else, so a matter OUTSIDE COMPETENCE - or one whose duty screen never ran - read 'ready to be relied on' while may_mark_reliance_ready refused it. Two owners of one judgement, disagreeing in the direction that matters. It is now a projection of AdviceReadiness, and a caller passing only the old two arguments gets the old answer WIDENED rather than a wrong one: an omitted screen is an unmet gate, never a passed one. | F152: P1 | G152: 1 | H152: fixed | I152: AB-04 / D16.4 | J152: test_reliance_is_derived_from_readiness_and_not_a_second_answer
A153: B-152 | B153: self-review before claiming AB-04 | C153: nm/app/server.py | D153: Nothing in the served path could create an Engagement | E153: So may_mark_reliance_ready refused every matter - correct, and useless, because nothing could ever call it. The contract existed and had no surface, the same shape as the conflict clearance before B-129. POST /matter/engagement is that surface, and D16.4's service terms are recorded and REPORTED rather than required: a client is entitled to have been told what this costs, but demanding a fee note before nm will think is the over-application that gets a control switched off. | F153: P1 | G153: 1 | H153: fixed | I153: AB-04 / D16.4 | J153: test_recording_an_engagement_opens_the_reliance_gate
A154: B-153 | B154: Phase 8 third review | C154: nm/core/urgency.py::Triage | D154: A carried history answered for a screen that never ran | E154: Eleven negative assessments from an earlier turn, overlaid on an empty screen from a provider outage, reported 'all 11 urgency classes cleared' - so a message saying the client had just been arrested passed on yesterday's 'no arrest'. The carry-forward I added to fix B-145 created this. Triage now carries screened_this_turn: what the MATTER knows is carried, whether THIS message was looked at is not. | F154: P1 | G154: 1 | H154: fixed | I154: AB-06 / D16.6 | J154: test_what_blocks_the_merits_is_not_having_looked
A155: B-154 | B155: Phase 8 third review | C155: nm/app/consult.py | D155: blocks_merits existed and nothing consulted it | E155: D16.6: a matter cannot enter ordinary analysis until every applicable class is cleared, ASSIGNED or escalated. The emergency led the answer and stopped nothing. Wired - and the definition corrected while wiring it: a LIVE urgency does not block, because Urgency refuses an APPLIES without an owner and an action so every live one is assigned by construction. What blocks is not having LOOKED. The old test asserted the stricter reading and was wrong. | F155: P1 | G155: 1 | H155: fixed | I155: AB-06 / D16.6 | J155: test_a_live_emergency_leads_by_date_and_does_NOT_block_the_merits
... A161: B-160 | B161: nm.tools.probe, first run | C161: nm/app/consult.py | D161: The readiness object was built as the one gate and the served path consulted one of its five permissions | E161: may_receive_substance, may_analyse and may_execute were defined and never called; consult.run read file_.may_hold_substance and turn.competence.blocks directly instead - the same answer today and TWO OWNERS OF IT tomorrow, which is the exact defect AdviceReadiness was written to remove. Found by the probe harness on its first run, in the object built to prevent it. | F161: P1 | G161: 1 | H161: fixed | I161: AB-03 / AB-02 / readiness | J161: test_the_uncleared_turn_still_answers_and_stores_nothing

Sheet Spikes
A1: ID | B1: Question | C1: Blocks | D1: Source | E1: Timebox | F1: Done when
A2: SP-01 | B2: Entailment check: cost and accuracy on the critical path | C2: V-06 | D2: Open Q1 | E2: 3d | F2: Latency and accuracy measured; a cheaper first pass with escalation decided or ruled out
A3: SP-02 | B3: How much of a real matter resolves structurally versus falls through to search | C3: R-02 | D3: Open Q2 | E3: 3d | F3: Resolved share measured on sampled real matters; ADR-1 curation cost confirmed or revisited
A4: SP-03 | B4: Merge-proposal accuracy on evidence short of a decisive identifier | C4: T-03 | D4: Open Q3 | E4: 2d | F4: Proposal precision measured; the interruption is justified or the threshold moves
A5: SP-04 | B5: Bounded evidence rounds: what the cap should be | C5: S-05 | D5: Open Q4 | E5: 2d | F5: Round distribution measured on real turns; cap set from data
A6: SP-05 | B6: Citator precision on a vetted sample before the flag is shown | C6: C-05 | D6: C5 | E6: 3d | F6: Precision and recall measured; display language set from the figure
A7: SP-06 | B7: OCR accuracy on Indian legal documents and scans | C7: DI-03 | D7: D10 | E7: 3d | F7: Per-format accuracy measured; confidence thresholds for the confirmation gate set
A8: SP-07 | B8: Cross-thread exposure: is it detectable at acceptable precision | C8: AD-02 | D8: D7C | E8: 3d | F8: Detection feasibility established on real multi-thread files
A9: SP-08 | B9: Inconsistent-theory detection feasibility | C9: TH-06 | D9: T3 | E9: 2d | F9: Whether contradictory factual accounts can be detected reliably enough to act on

Sheet Baseline
A1: Quantity | B1: Value | C1: Unit | D1: Measured on | E1: Direction | F1: Method | G1: Target | H1: Note
A2: citator.candidate_recall_pct | B2: 21 | C2: % | D2: 2026-08-27 | E2: higher_is_better | F2: candidates() over a stride-22 sample of the judgment tree: 1,548 judgments, 16,569 paragraphs, 3,472 naming a cited case. The stride is recorded so the figure can be reproduced (nm/tools/draw_gold_set.py) | G2: Measured against a hand-vetted sample before the flag is shown (C-04) | H2: Was 21.1% on a sample whose stride was never recorded. Re-measured after citation spans were anchored on their mention; measured separately, normalising whitespace before matching changes no pattern's match count (versus/supra/reporter all identical), so the fix moved what a mention CARRIES and not what is found.
A3: citator.entries | B3: 4894 | C3: cases | D3: 2026-08-26 | E3: informational | F3: citator.json | G3: - | H3: Regex-derived. Replaced by C-02 with measured precision.
A4: citator.flagged_negative | B4: 1317 | C4: cases | D4: 2026-08-26 | E4: informational | F4: citator.json | G4: -
A5: citator.gold_set_population | B5: 24263 | C5: mentions | D5: 2026-08-27 | E5: higher_is_better | F5: every citation mention in the stride-22 sample, the population the 200 are drawn from | G5: - | H5: Was 21,400 before the paragraph-segmentation fix (B-62): more paragraphs read means more paragraphs naming a cited case. A sample size means nothing without the population it came from, which is why this is recorded.
A6: citator.gold_set_size | B6: 200 | C6: items | D6: 2026-08-27 | E6: informational | F6: Uniform random over 26,817 candidate mentions, seed 20260827 | G6: Vetted by a person before any precision or recall figure is quoted | H6: Drawn, not composed (C5D). Awaiting hand-vetting: the vetter field is empty and CitatorMeasurement refuses to emit flag text until it is filled.
A7: citator.gold_set_span_carries_its_mention_pct | B7: 100 | C7: % | D7: 2026-08-27 | E7: higher_is_better | F7: nm/tools/draw_gold_set.py, reported at draw time over all 200 items | G7: 100% - below it the set is not vettable | H7: Was 8% (16 of 200): the span was the paragraph's opening 320 characters regardless of where the mention sat, so 184 of 200 items did not contain the case they were drawn for. The set was unvettable by a person and by a model alike, and it looked perfectly well-formed.
A8: classification.discard_pct | B8: 20.1 | C8: % | D8: 2026-08-26 | E8: lower_is_better | F8: 641 of 3,192 issue labels across every stored matter | G8: 0 - F2 removes the delete path | H8: Led by limitation (122), bail (86), forum/jurisdiction (58).
A9: corpus.act_ids | B9: 3207 | C9: act_ids | D9: 2026-08-27 | E9: informational | F9: Distinct act_id in bareacts_v3_chunks | G9: - | H9: Two naming conventions coexist: 'UNION OF INDIA_1961_0_THE INCOME TAX ACT, 1961' and 'the_income_tax_act_1961'.
A10: corpus.act_subjects | B10: 1648 | C10: subjects | D10: 2026-08-27 | E10: informational | F10: act_ids after normalising away the convention prefix | G10: - | H10: The true number of distinct Acts. 3,207 ids describe 1,648 subjects.
A11: corpus.acts_duplicated_pct | B11: 93.5 | C11: % | D11: 2026-08-27 | E11: lower_is_better | F11: 1541 of 1648 subjects held under >1 act_id; ALL are prefixed-vs-snake_case collisions, zero same-convention groups | G11: 0 after I-06 | H11: 375,923 of 414,710 chunks sit in duplicated subjects.
A12: corpus.acts_with_numbering_holes | B12: 403 | C12: subjects | D12: 2026-08-27 | E12: lower_is_better | F12: Sections absent below the highest each Act itself holds, across both stores | G12: Falls as I-10 then I-09 land | H12: 91 thinly ingested, 312 where a year or date is stored as a section number. Of 27 intended subjects, 11 have holes and 6 of those are mis-numbering.
A13: corpus.case_paragraphs | B13: 1015756 | C13: paragraphs | D13: 2026-08-27 | E13: informational | F13: Count of caselaws chunk store | G13: -
A14: corpus.cited_cases_populated_pct | B14: 1.5 | C14: % | D14: 2026-08-27 | E14: informational | F14: Same sample; misses 92.3% of citing paragraphs | G14: - | H14: Cannot serve as a recall net. Superseded by story C-01.
A15: corpus.dedup_by_convention_is_lossy | B15: 1 | C15: bool | D15: 2026-08-27 | E15: informational | F15: Sampled four Acts: Income Tax 1961 has 611 sections only in the prefixed copy and 130 only in the snake copy; Merchant Shipping 1958 has 351 only in prefixed; Wild Life 1972 and Fertilizer Order 1985 have sections only in snake | G15: - | H15: MEASURED REFUSAL: deleting either convention wholesale destroys real sections. Any dedup must merge on normalised subject + section and keep the UNION (story I-06).
A16: corpus.judgments | B16: 33791 | C16: judgments | D16: 2026-08-27 | E16: informational | F16: Count of caselaws parent store | G16: -
A17: corpus.paragraphs_attributable_pct | B17: 44.4 | C17: % | D17: 2026-08-27 | E17: higher_is_better | F17: paragraph_type distribution: reasoning + ratio + order | G17: Raise via story I-04
A18: corpus.paragraphs_counsel_arguments_pct | B18: 14.8 | C18: % | D18: 2026-08-27 | E18: informational | F18: paragraph_type distribution | G18: - | H18: Must be excluded from attribution, not reduced. 149,960 paragraphs.
A19: corpus.paragraphs_naming_a_case_pct | B19: 19.3 | C19: % | D19: 2026-08-27 | E19: informational | F19: Regex floor over a 40,000-paragraph random sample | G19: - | H19: A floor: counts only explicit X v Y forms.
A20: corpus.paragraphs_unclassified_pct | B20: 26.7 | C20: % | D20: 2026-08-27 | E20: lower_is_better | F20: paragraph_type distribution | G20: Near zero after I-04
A21: corpus.raw_acts_with_a_commencement_header_pct | B21: 94 | C21: % | D21: 2026-08-27 | E21: informational | F21: `Commenced on <date>` header in the raw .txt sources: 1,555 of 1,655 files | G21: - | H21: The ceiling for I-05. The ingested stores carry no commencement field at all.
A22: corpus.section_heads | B22: 50800 | C22: rows | D22: 2026-08-27 | E22: informational | F22: bareacts_v3_parents.json, the section-level store | G22: - | H22: 36,069 distinct (act, section) pairs - 14,731 duplicate rows across 465 Acts (B-58).
A23: corpus.telangana_hc_judgments | B23: 0 | C23: judgments | D23: 2026-08-27 | E23: higher_is_better | F23: Court read from each document's own header, not from its directory | G23: Non-zero, 2019 onward | H23: CONFIRMED FROM THE DOCUMENTS: 29,748 name themselves Supreme Court of India (1950-2026) and 4,289 name themselves Andhra HC (Pre-Telangana) (1954-2018). The raw tree holds NOTHING after 2018, so B-13 is a sourcing problem and not an ingestion one.
A24: drafting.retrieval_paths | B24: 0 | C24: paths | D24: 2026-08-28 | E24: lower_is_better | F24: layercheck: nm.drafting may import nm.core, nm.ports, nm.obs only; asserted again by reading the AST of every module in the layer | G24: 0 | H24: DR2 as a build failure rather than a promise. D5 depends on there being exactly one grounding path, and a second one is not reviewable into existence.
A25: drafting.verification_checks | B25: 9 | C25: checks | D25: 2026-08-28 | E25: higher_is_better | F25: nm/drafting/verify.py::CHECKS, all of which run | G25: - | H25: The legacy verifier declared 8 and RAN 3: five returned not_implemented with ok=True, and a sixth reported skipped as a pass. The count is only comparable because none of these nine can report success without running (B-72).
A26: graph.acts_with_a_read_commencement_pct | B26: 15.2 | C26: % | D26: 2026-08-27 | E26: higher_is_better | F26: Commencement clause read from each Act's own section 1: 240 of 1,648 subjects | G26: Raise via I-01 (ingest commencement notifications) | H26: 250 of 1,648 subjects. 345 more defer commencement to a Government notification; 1,053 state nothing. But 94% of the RAW Act files carry an explicit `Commenced on` header that ingestion discards, so this is metadata thrown away rather than a corpus gap (B-48).
A27: graph.build_seconds | B27: 287 | C27: s | D27: 2026-08-27 | E27: lower_is_better | F27: Full-corpus deterministic build, wall clock | G27: - | H27: Full-corpus deterministic build across both bare-act stores, wall clock. Rebuild from the same sources is byte-identical (K-10).
A28: graph.cross_reference_edges | B28: 45512 | C28: edges | D28: 2026-08-27 | E28: informational | F28: Distinct evidenced cross-reference edges, full-corpus build | G28: - | H28: Distinct evidenced cross-reference edges across both stores. Every edge carries a verbatim span and a locator (G15).
A29: graph.judgment_interprets_resolution_pct | B29: 32 | C29: % | D29: 2026-08-27 | E29: higher_is_better | F29: Provision references in judgment paragraphs resolving to a held provision, 1,500-judgment sample | G29: Rises as ingestion closes coverage gaps | H29: 19,662 references found; the 68% that do not resolve are kept as counted candidates rather than dropped. Legacy case_section_links held 0 rows.
A30: graph.provisions | B30: 173562 | C30: provisions | D30: 2026-08-27 | E30: informational | F30: Full-corpus legal graph build, section heads and schedule articles (G20) | G30: - | H30: Corrected: the earlier 122,762 read only one of the two bare-act stores (B-57). 1,648 Acts, section heads and schedule articles across both.
A31: graph.repeal_edges | B31: 24 | C31: edges | D31: 2026-08-27 | E31: informational | F31: Act-level repeals read from the repealing provision's own text | G31: - | H31: Act-level repeals read from the repealing provision's own text; 203 further Acts are named as repealed but absent from the corpus.
A32: graph.unsatisfied_references | B32: 6917 | C32: references | D32: 2026-08-27 | E32: lower_is_better | F32: Cross-references resolving to a provision the corpus does not hold, kept as candidates | G32: Falls as I-01 closes ingestion gaps | H32: Cross-references resolving to a provision the corpus does not hold, kept as candidates - a derived ingestion backlog rather than a silent loss (B-49).
... A76: turn.retrieval_seconds | B76: 13.9 | C76: s | D76: 2026-08-26 | E76: lower_is_better | F76: Stage instrumentation | G76: - | H76: Legacy system.

Sheet Summary
A1: Roll-up
A2: Every figure is a formula over Backlog. Nothing here is typed in.
A4: Phase | B4: Stories | C4: Points | D4: Known | E4: Needs meas. | F4: Unknown
A5: Phase 0 - Foundation | B5: =COUNTIF(Backlog!$B$2:$B$218,$A5) | C5: =SUMIF(Backlog!$B$2:$B$218,$A5,Backlog!$H$2:$H$218) | D5: =COUNTIFS(Backlog!$B$2:$B$218,$A5,Backlog!$I$2:$I$218,"Known") | E5: =COUNTIFS(Backlog!$B$2:$B$218,$A5,Backlog!$I$2:$I$218,"Needs measurement") | F5: =COUNTIFS(Backlog!$B$2:$B$218,$A5,Backlog!$I$2:$I$218,"Unknown until instrumented")
A6: Phase 1 - Knowledge | B6: =COUNTIF(Backlog!$B$2:$B$218,$A6) | C6: =SUMIF(Backlog!$B$2:$B$218,$A6,Backlog!$H$2:$H$218) | D6: =COUNTIFS(Backlog!$B$2:$B$218,$A6,Backlog!$I$2:$I$218,"Known") | E6: =COUNTIFS(Backlog!$B$2:$B$218,$A6,Backlog!$I$2:$I$218,"Needs measurement") | F6: =COUNTIFS(Backlog!$B$2:$B$218,$A6,Backlog!$I$2:$I$218,"Unknown until instrumented")
A7: Phase 2 - Evidence | B7: =COUNTIF(Backlog!$B$2:$B$218,$A7) | C7: =SUMIF(Backlog!$B$2:$B$218,$A7,Backlog!$H$2:$H$218) | D7: =COUNTIFS(Backlog!$B$2:$B$218,$A7,Backlog!$I$2:$I$218,"Known") | E7: =COUNTIFS(Backlog!$B$2:$B$218,$A7,Backlog!$I$2:$I$218,"Needs measurement") | F7: =COUNTIFS(Backlog!$B$2:$B$218,$A7,Backlog!$I$2:$I$218,"Unknown until instrumented")
A8: Phase 3 - Analysis | B8: =COUNTIF(Backlog!$B$2:$B$218,$A8) | C8: =SUMIF(Backlog!$B$2:$B$218,$A8,Backlog!$H$2:$H$218) | D8: =COUNTIFS(Backlog!$B$2:$B$218,$A8,Backlog!$I$2:$I$218,"Known") | E8: =COUNTIFS(Backlog!$B$2:$B$218,$A8,Backlog!$I$2:$I$218,"Needs measurement") | F8: =COUNTIFS(Backlog!$B$2:$B$218,$A8,Backlog!$I$2:$I$218,"Unknown until instrumented")
A9: Phase 4 - Delivery | B9: =COUNTIF(Backlog!$B$2:$B$218,$A9) | C9: =SUMIF(Backlog!$B$2:$B$218,$A9,Backlog!$H$2:$H$218) | D9: =COUNTIFS(Backlog!$B$2:$B$218,$A9,Backlog!$I$2:$I$218,"Known") | E9: =COUNTIFS(Backlog!$B$2:$B$218,$A9,Backlog!$I$2:$I$218,"Needs measurement") | F9: =COUNTIFS(Backlog!$B$2:$B$218,$A9,Backlog!$I$2:$I$218,"Unknown until instrumented")
A10: Phase 5 - Drafting | B10: =COUNTIF(Backlog!$B$2:$B$218,$A10) | C10: =SUMIF(Backlog!$B$2:$B$218,$A10,Backlog!$H$2:$H$218) | D10: =COUNTIFS(Backlog!$B$2:$B$218,$A10,Backlog!$I$2:$I$218,"Known") | E10: =COUNTIFS(Backlog!$B$2:$B$218,$A10,Backlog!$I$2:$I$218,"Needs measurement") | F10: =COUNTIFS(Backlog!$B$2:$B$218,$A10,Backlog!$I$2:$I$218,"Unknown until instrumented")
A11: Phase 6 - Enterprise | B11: =COUNTIF(Backlog!$B$2:$B$218,$A11) | C11: =SUMIF(Backlog!$B$2:$B$218,$A11,Backlog!$H$2:$H$218) | D11: =COUNTIFS(Backlog!$B$2:$B$218,$A11,Backlog!$I$2:$I$218,"Known") | E11: =COUNTIFS(Backlog!$B$2:$B$218,$A11,Backlog!$I$2:$I$218,"Needs measurement") | F11: =COUNTIFS(Backlog!$B$2:$B$218,$A11,Backlog!$I$2:$I$218,"Unknown until instrumented")
A12: TOTAL | B12: =SUM(B5:B11) | C12: =SUM(C5:C11) | D12: =SUM(D5:D11) | E12: =SUM(E5:E11) | F12: =SUM(F5:F11)
A14: Coverage check
A15: PRD decisions logged | B15: =COUNTA('PRD Coverage'!$A$2:$A$215)
A16: Decisions with no story | B16: =COUNTIF('PRD Coverage'!$E$2:$E$215,"UNMAPPED")
A17: Stories in backlog | B17: =COUNTA(Backlog!$A$2:$A$218)
A18: Dependency edges | B18: =COUNTA(Dependencies!$A$2:$A$268)
A19: Decisions that are working agreements (n/a) | B19: =COUNTIF('PRD Coverage'!$D$2:$D$215,"PROCESS")
A20: A non-zero 'Decisions with no story' is a real gap, not a formatting artefact - it means a PRD rule nobody is building.
A23: Progress
A24: Phase | B24: decided | C24: built | D24: tested | E24: verified live | F24: % at least built
A25: Phase 0 - Foundation | B25: =COUNTIFS(Backlog!$B$2:$B$218,$A25,Backlog!$N$2:$N$218,"decided") | C25: =COUNTIFS(Backlog!$B$2:$B$218,$A25,Backlog!$N$2:$N$218,"built") | D25: =COUNTIFS(Backlog!$B$2:$B$218,$A25,Backlog!$N$2:$N$218,"tested") | E25: =COUNTIFS(Backlog!$B$2:$B$218,$A25,Backlog!$N$2:$N$218,"verified live") | F25: =IF(COUNTIF(Backlog!$B$2:$B$218,$A25)=0,0,COUNTIFS(Backlog!$B$2:$B$218,$A25,Backlog!$N$2:$N$218,"<>decided")/COUNTIF(Backlog!$B$2:$B$218,$A25))
A26: Phase 1 - Knowledge | B26: =COUNTIFS(Backlog!$B$2:$B$218,$A26,Backlog!$N$2:$N$218,"decided") | C26: =COUNTIFS(Backlog!$B$2:$B$218,$A26,Backlog!$N$2:$N$218,"built") | D26: =COUNTIFS(Backlog!$B$2:$B$218,$A26,Backlog!$N$2:$N$218,"tested") | E26: =COUNTIFS(Backlog!$B$2:$B$218,$A26,Backlog!$N$2:$N$218,"verified live") | F26: =IF(COUNTIF(Backlog!$B$2:$B$218,$A26)=0,0,COUNTIFS(Backlog!$B$2:$B$218,$A26,Backlog!$N$2:$N$218,"<>decided")/COUNTIF(Backlog!$B$2:$B$218,$A26))
A27: Phase 2 - Evidence | B27: =COUNTIFS(Backlog!$B$2:$B$218,$A27,Backlog!$N$2:$N$218,"decided") | C27: =COUNTIFS(Backlog!$B$2:$B$218,$A27,Backlog!$N$2:$N$218,"built") | D27: =COUNTIFS(Backlog!$B$2:$B$218,$A27,Backlog!$N$2:$N$218,"tested") | E27: =COUNTIFS(Backlog!$B$2:$B$218,$A27,Backlog!$N$2:$N$218,"verified live") | F27: =IF(COUNTIF(Backlog!$B$2:$B$218,$A27)=0,0,COUNTIFS(Backlog!$B$2:$B$218,$A27,Backlog!$N$2:$N$218,"<>decided")/COUNTIF(Backlog!$B$2:$B$218,$A27))
A28: Phase 3 - Analysis | B28: =COUNTIFS(Backlog!$B$2:$B$218,$A28,Backlog!$N$2:$N$218,"decided") | C28: =COUNTIFS(Backlog!$B$2:$B$218,$A28,Backlog!$N$2:$N$218,"built") | D28: =COUNTIFS(Backlog!$B$2:$B$218,$A28,Backlog!$N$2:$N$218,"tested") | E28: =COUNTIFS(Backlog!$B$2:$B$218,$A28,Backlog!$N$2:$N$218,"verified live") | F28: =IF(COUNTIF(Backlog!$B$2:$B$218,$A28)=0,0,COUNTIFS(Backlog!$B$2:$B$218,$A28,Backlog!$N$2:$N$218,"<>decided")/COUNTIF(Backlog!$B$2:$B$218,$A28))
A29: Phase 4 - Delivery | B29: =COUNTIFS(Backlog!$B$2:$B$218,$A29,Backlog!$N$2:$N$218,"decided") | C29: =COUNTIFS(Backlog!$B$2:$B$218,$A29,Backlog!$N$2:$N$218,"built") | D29: =COUNTIFS(Backlog!$B$2:$B$218,$A29,Backlog!$N$2:$N$218,"tested") | E29: =COUNTIFS(Backlog!$B$2:$B$218,$A29,Backlog!$N$2:$N$218,"verified live") | F29: =IF(COUNTIF(Backlog!$B$2:$B$218,$A29)=0,0,COUNTIFS(Backlog!$B$2:$B$218,$A29,Backlog!$N$2:$N$218,"<>decided")/COUNTIF(Backlog!$B$2:$B$218,$A29))
A30: Phase 5 - Drafting | B30: =COUNTIFS(Backlog!$B$2:$B$218,$A30,Backlog!$N$2:$N$218,"decided") | C30: =COUNTIFS(Backlog!$B$2:$B$218,$A30,Backlog!$N$2:$N$218,"built") | D30: =COUNTIFS(Backlog!$B$2:$B$218,$A30,Backlog!$N$2:$N$218,"tested") | E30: =COUNTIFS(Backlog!$B$2:$B$218,$A30,Backlog!$N$2:$N$218,"verified live") | F30: =IF(COUNTIF(Backlog!$B$2:$B$218,$A30)=0,0,COUNTIFS(Backlog!$B$2:$B$218,$A30,Backlog!$N$2:$N$218,"<>decided")/COUNTIF(Backlog!$B$2:$B$218,$A30))
A31: Phase 6 - Enterprise | B31: =COUNTIFS(Backlog!$B$2:$B$218,$A31,Backlog!$N$2:$N$218,"decided") | C31: =COUNTIFS(Backlog!$B$2:$B$218,$A31,Backlog!$N$2:$N$218,"built") | D31: =COUNTIFS(Backlog!$B$2:$B$218,$A31,Backlog!$N$2:$N$218,"tested") | E31: =COUNTIFS(Backlog!$B$2:$B$218,$A31,Backlog!$N$2:$N$218,"verified live") | F31: =IF(COUNTIF(Backlog!$B$2:$B$218,$A31)=0,0,COUNTIFS(Backlog!$B$2:$B$218,$A31,Backlog!$N$2:$N$218,"<>decided")/COUNTIF(Backlog!$B$2:$B$218,$A31))
A32: Phase 7 - Integration | B32: =COUNTIFS(Backlog!$B$2:$B$218,$A32,Backlog!$N$2:$N$218,"decided") | C32: =COUNTIFS(Backlog!$B$2:$B$218,$A32,Backlog!$N$2:$N$218,"built") | D32: =COUNTIFS(Backlog!$B$2:$B$218,$A32,Backlog!$N$2:$N$218,"tested") | E32: =COUNTIFS(Backlog!$B$2:$B$218,$A32,Backlog!$N$2:$N$218,"verified live") | F32: =IF(COUNTIF(Backlog!$B$2:$B$218,$A32)=0,0,COUNTIFS(Backlog!$B$2:$B$218,$A32,Backlog!$N$2:$N$218,"<>decided")/COUNTIF(Backlog!$B$2:$B$218,$A32))
A34: Defects
A35: Severity | B35: open | C35: fixed | D35: withdrawn | E35: open points
A36: P1 | B36: =COUNTIFS(Bugs!$F$2:$F$161,$A36,Bugs!$H$2:$H$161,"open") | C36: =COUNTIFS(Bugs!$F$2:$F$161,$A36,Bugs!$H$2:$H$161,"fixed") | D36: =COUNTIFS(Bugs!$F$2:$F$161,$A36,Bugs!$H$2:$H$161,"withdrawn") | E36: =SUMIFS(Bugs!$G$2:$G$161,Bugs!$F$2:$F$161,$A36,Bugs!$H$2:$H$161,"open")
A37: P2 | B37: =COUNTIFS(Bugs!$F$2:$F$161,$A37,Bugs!$H$2:$H$161,"open") | C37: =COUNTIFS(Bugs!$F$2:$F$161,$A37,Bugs!$H$2:$H$161,"fixed") | D37: =COUNTIFS(Bugs!$F$2:$F$161,$A37,Bugs!$H$2:$H$161,"withdrawn") | E37: =SUMIFS(Bugs!$G$2:$G$161,Bugs!$F$2:$F$161,$A37,Bugs!$H$2:$H$161,"open")
A38: P3 | B38: =COUNTIFS(Bugs!$F$2:$F$161,$A38,Bugs!$H$2:$H$161,"open") | C38: =COUNTIFS(Bugs!$F$2:$F$161,$A38,Bugs!$H$2:$H$161,"fixed") | D38: =COUNTIFS(Bugs!$F$2:$F$161,$A38,Bugs!$H$2:$H$161,"withdrawn") | E38: =SUMIFS(Bugs!$G$2:$G$161,Bugs!$F$2:$F$161,$A38,Bugs!$H$2:$H$161,"open")
A39: TOTAL | B39: =SUM(B36:B38) | C39: =SUM(C36:C38) | D39: =SUM(D36:D38) | E39: =SUM(E36:E38)

Sheet Advocate Behaviour
A1: Great Advocate Behaviour - implementation audit
A2: 28 PRD D16 tenets reviewed against the local code graph, source and tests on 2026-08-28. Status is conservative: offline contracts do not count as served behaviour.
A4: Total tenets | B4: =COUNTA(A8:A35) | C4: Implemented | D4: =COUNTIF(D8:D35,"Implemented") | E4: Partial | F4: =COUNTIF(D8:D35,"Partial") | G4: Contract only | H4: =COUNTIF(D8:D35,"Contract only") | I4: Not implemented | J4: =COUNTIF(D8:D35,"Not implemented") | K4: P0 priorities | L4: =COUNTIF(J8:J35,"P0")
A5: Reading rule: Implemented = behaviour exists with meaningful tests; Partial = useful pieces exist but the end-to-end behaviour is incomplete; Contract only = strong types/tests exist but the served consultation does not execute them; Not implemented = no material implementation found.
A6: Priority rule: P0 blocks safe professional reliance; P1 is needed for a complete advocate workflow; P2 is important specialist or service depth. Human-practice items remain explicit: NM should prompt, record, verify or refuse, not claim to perform the advocate's human act.
A7: ID | B7: Behavioural tenet | C7: PRD | D7: Implementation status | E7: How good | F7: What is already covered | G7: Code and test evidence | H7: Main gap | I7: How it needs to improve | J7: Priority | K7: Proposed acceptance / verification | L7: Execution boundary | M7: Research / specification basis
A8: AB-01 | B8: Professional stance | C8: D16.1 | D8: Complete | E8: Strong | F8: The standing advocate prompt requires a committed senior-counsel view, corpus grounding, adverse-risk disclosure and no invented law. Identity, access control, privacy diagnostics and citation verification protect parts of confidentiality and candour. | G8: nm/core/duty.py - a closed 7-item Breach list, each carrying its own 'Not:' clause, and the BOUND written before the code: an advocate owes candour to the COURT and owes the opponent nothing. 'Do not volunteer that document' is proper; 'do not cite the binding judgment' is a breach, and the duty is the whole difference. A Finding cannot exist without the words it read and the LAWFUL COURSE, because a refusal an advocate cannot act on is one they route around. Second fail-closed path in the system alongside grounding; a screen that did not run is not clean and does not block. advocate.DUTY on the strong tier. LIVE PROBE, both directions: improper draft blocked with both breaches caught, quoted, and the lawful course named; a draft saying 'put them to strict proof', 'do not admit', 'not obliged to volunteer our survey report', 'press for costs' returned CLEAR. | H8: The screen reads the produced advice only. It does not yet see the instruction the advocate gave, so an improper instruction that the persona already refuses upstream is never presented to it. Conflicts and discrimination are in the list but have no separate detection beyond the model's reading. EXTERNAL REVIEW (B-125): rated Partial / Weak, and correctly. The screen was fail-closed in the type and FAIL-OPEN IN THE PRODUCT — the answer streamed to the browser token by token and the duty review ran afterwards, so a recommendation to suppress authority was read before it was blocked, and no later payload unreads it. Fixed: the answer is buffered, screened, then emitted once, with an order invariant test and the page taking the final payload as authoritative. Verified live on a served turn: one token event, after the duty stage. Held at Partial because the screen still reads only the produced advice and has no live both-directions run since the ordering change. | I8: Create a ProfessionalDuty assessment before recommendation and drafting. It should classify legality, duty to court, candour/adverse authority, confidentiality, conflict and improper means; block or redirect a failed assessment and preserve the reason. | J8: P0 | K8: A recommendation that proposes deception, concealment, a knowingly false case or suppression of controlling adverse authority is blocked and replaced with the lawful course. | L8: NM guardrail + human professional decision | M8: BCI Rules; Supreme Court 2024 INSC 410; PRD D16.1
A9: AB-02 | B9: Competence | C9: D16.2 | D9: Complete | E9: Strong | F9: Coverage states, explicit degradation, bounded evidence rounds, release status, cost/quality gates and owner-bearing compliance gaps make technical inability visible rather than silently passing. | G9: nm/core/competence.py - competence is never a judgement about difficulty; it is one comparison, what the matter REQUIRES against what nm DECLARES it holds, and the halves are computed by different things: the model names the requirement, the CODE decides whether it is met. Only two capabilities can block and both are limits of nm itself - the test is whether nm would answer anyway and the answer would READ CORRECTLY. An expert, local counsel, a specialism, supervision are requirements of the CASE: named in the advice, never stopping it. A language cannot block a jurisdiction we hold, structurally - we declared the law we hold, so a contrary answer is a finding about the declaration, not about the matter. Silence and uncertainty never block; a named absence does. Wired into the served turn before the merits and before the corpus is touched. LIVE, three directions: a Kerala rent matter BLOCKS and names counsel practising where it is governed; a Telangana / central matter is clean; an acquisition matter names a handwriting expert and does not block. | H9: The declaration is one line in the composition root and nothing checks it against what the corpus actually holds - if the corpus gains a state and the line does not, nm refuses matters it could take. TIME (whether the work fits the time available) is in D16.2 and is not modelled: nm has no view of its own queue. EXTERNAL REVIEW (B-126, B-127): two holes, both fixed. The assessment was recomputed from the latest message and not held on the matter, so a reply that said nothing about jurisdiction was read as though it had cleared a block; and the language exclusion DELETED a finding instead of moving it, so an unheld language on a held jurisdiction produced neither refusal nor referral. Graded down from Strong: the declaration is still one line in the composition root that nothing checks against the corpus, and the two-turn bypass has not been re-verified live. | I9: Add a matter-level CompetenceAssessment with required domains, jurisdiction, language, complexity, available time, supervision and referral/escalation. Make an unmet material requirement an open gate, not a disclaimer. | J9: P1 | K9: A matter outside declared competence cannot be marked advice-ready; it names the missing competence and the referral, supervision or escalation needed. | L9: NM assessment + human acceptance/referral | M9: BCI Rules; BSB Professional Statement; SRA Competence; PRD D16.2
A10: AB-03 | B10: Before receiving substance | C10: D16.3 | D10: Complete | E10: Strong | F10: Matter access is deny-by-default after an advocate, session and grant exist. The in-process store enforces matter isolation. | G10: nm/core/engagement.py - ConflictState is three-state so NOT_RUN is not a shade of CLEAR; screen() reports matches and never decides what they mean; Clearance CANNOT BE CONSTRUCTED without the human who gave it, which is the audit's own execution boundary enforced by the type rather than recorded in a plan. Quarantine holds substance out of the file and records whether it was released or discarded and why (D16.3 asks what happens to information already received). EmergencyException is the stated bound, authorised and attributable. nm/tests/a_logic/test_engagement.py. | H10: The served path does not yet COLLECT parties before substance or hold the first message in quarantine - the types and gates exist, the pre-intake envelope in the UI does not. No firm-wide registry of prior matters to screen against. EXTERNAL REVIEW (B-129): confirmed as a release blocker. The served path merges role, cause and date onto the file before anything consults may_hold_substance, and screen()/Quarantine have no production caller. Not closed: refusing to hold substance until a clearance that no surface can give would stop the product, so the file now CARRIES holds_uncleared_substance and the board shows it. Stated rather than prevented, and left open in the register. | I10: Introduce a minimal pre-intake envelope and conflict service. Collect only identities and matter descriptors, run exact plus reviewed fuzzy matches, define emergency exceptions, quarantine conflicted substance and record clearance authority. | J10: P0 | K10: A substantive message cannot enter a matter store until conflict clearance or an expressly authorised emergency exception exists. | L10: Human conflict decision supported by NM | M10: BCI Rules; BSB Professional Statement; PRD D16.3
A11: AB-04 | B11: Authority and engagement | C11: D16.4 | D11: Complete | E11: Strong | F11: The enterprise identity model distinguishes advocates, chambers, sessions, capabilities, grants and purposes, and audits every access decision. | G11: nm/core/engagement.py::Engagement refuses to exist without client, instructor, decision owner and scope - three roles that are often three people, and the one that goes missing is the decision owner, because an intermediary who instructs is not always entitled to settle. reliance() is read on every served turn and shown on the board, and the answer says in terms that it is a preliminary view pending engagement and a conflict check. Live: that line appears. | H11: Fees, disbursements, custody, termination and the complaints route are not recorded. Nothing yet requires fresh authority for an irreversible step - that is AB-20's DecisionRecord. EXTERNAL REVIEW: rating aligned to Moderate. Fees, disbursements, custody, termination and the complaints route are still unrecorded, and the reliance note is the only served consequence. | I11: Add Engagement, ClientIdentity, InstructionAuthority and DecisionAuthority records. Gate reliance on confirmed client identity, scope and authority; surface exclusions and require explicit authority for settlement, filing and irreversible steps. | J11: P0 | K11: Advice cannot be marked ready for reliance until client, instructor, decision owner and scope are recorded; out-of-scope work is blocked or expressly accepted. | L11: Human engagement + NM record/gates | M11: BCI Rules; BSB client research; SRA Competence; PRD D16.4
A12: AB-05 | B12: First human contact | C12: D16.5 | D12: Not implemented | E12: Weak | F12: The served opening distinguishes a greeting from a brief, responds conversationally, states a mode and uses a plain-language senior-counsel voice instead of immediately presenting a form. | G12: nm/app/intake.py::carries_a_brief; nm/core/advocate.py::OPENING; nm/core/mode.py; test_talking.py; test_phase4_queue.py | H12: No client communication profile records language, accessibility, privacy, vulnerability, support needs, preferred channel or expectations. The product serves advocates only, so the human client's contact still sits outside the model. | I12: Add a communication and vulnerability profile for the instructing advocate to record, with a short opening protocol and reasonable-adjustment flags. Keep it proportionate and avoid forcing full intake before an urgent issue is heard. | J12: P2 | K12: The opening records or expressly clears communication preference, accessibility, privacy, vulnerability, urgency and expectation-setting without treating a greeting as a matter. | L12: Human-led contact + NM prompts | M12: BSB client research; SRA Competence; PRD D16.5
A13: AB-06 | B13: Emergency triage | C13: D16.6 | D13: Complete | E13: Strong | F13: Limitation is computed early; posture and limitation are blocking gates; deadline changes re-orient the answer; passed and near deadlines lead; loud signals cannot be collapsed. | G13: nm/core/urgency.py (closed 11-class taxonomy, coverage by set equality, an applicable urgency refused without consequence/action/owner/date); nm/app/triage.py (malformed lines DROPPED, silence never read as clearance); nm/core/advocate.py::URGENCY; wired before merits in nm/app/consult.py with _urgent_lead prepended to BOTH the question and the advice path; nm/tests/a_logic/test_urgency.py (11 tests). Live: the observed failure now leads with safety, owner and date. VALIDATED over all 18 golden scenarios: triage complete 18/18; urgencies per scenario {0:6, 1:10, 2:1, 4:1} (median 1, not the 5-of-11 the first prompt produced); classes land where an advocate would put them - all 4 bail matters flagged liberty, child_safety on matri-06. 18 calls, 20,866 tokens. | H13: Urgency is mostly limitation-shaped. There is no complete triage for arrest/liberty, safety, child protection, evidence destruction, asset dissipation, injunction/status quo, service, hearing or order compliance. | I13: Create a closed UrgencyKind taxonomy, triage every new matter before merits, and require consequence, immediate action, owner and time. Make applicable unresolved emergencies blocking and visible above ordinary advice. | J13: P0 | K13: Every new matter clears all urgency classes; a material emergency appears first with an owned action and time, while a non-applicable class records why. | L13: NM triage + human emergency action | M13: BCI duty of competence; CPS casework standards; PRD D16.6
A14: AB-07 | B14: Client interview | C14: D16.7 | D14: Partial | E14: Weak | F14: Document-first intake, source-carrying facts, confirmation gates, preserved contradictions, ranked gap questions, one-question batches and a single guided re-ask support disciplined clarification. | G14: nm/core/interview.py - adds the axis Fact.certainty is not. Certainty answers where a statement came from; Basis answers whether the speaker can GIVE EVIDENCE of it, and the two are orthogonal: 'the wall went up in 2022' is asserted either way, and whether the client watched it decides whether an element is proved or believed. Six states, and UNSTATED is not DIRECT - treating silence as 'he saw it' is how a case reaches trial resting on something nobody witnessed. A hearsay or document basis must name what it points at. A recorded 'exact words' must be FINDABLE IN THE ACCOUNT, which is the one check here against invention rather than sloppiness. The narrative is kept as given and nothing edits it; only the propositions the client cannot prove alone reach the position, so an advocate is not told which parts of the account their own client witnessed. leads() scopes the non-leading rule to material contested facts, because leading is proper on background. LIVE, both directions: a plainly-told brief produces nothing to chase; an account resting on a brother and a neighbour flags 6 of 7 with their sources named. | H14: Two of the four acceptance limbs are contracts rather than served behaviour. leads() is tested but the question path still builds its text from advocate.QUESTION without consulting it, and Summary always stands NOT_PUT because there is no surface through which a client confirms or corrects one - the same execution boundary as a conflict clearance, and the same missing half. Witness interviewing is not separated from client instruction-taking. | I14: Add an InterviewRecord with proposition source type, knowledge basis, exact words where material, summary confirmation and correction. Sequence open narrative before gap questions, and keep witness interviewing separate from client instruction-taking. | J14: P1 | K14: A sampled interview preserves an uninterrupted account, labels each material proposition's knowledge basis, asks non-leading clarifiers and produces a confirmable summary with contradictions intact. | L14: NM interview workflow + human judgement | M14: BSB Professional Statement; SRA Competence; PRD D16.7
A15: AB-08 | B15: Objectives and constraints | C15: D16.8 | D15: Partial | E15: Weak | F15: Thread objective is typed; defending work is constrained to containment; theory ranks reliefs; proceeding advice records what would change a no-go view and the cost of proceeding anyway. | G15: nm/core/objectives.py - deliberately NOT matter.Objective, which says what we are trying to win. This says what the client wants out of their life, and the second routinely overrules the first: a client who will win in four years and be out of business in two does not want the decree. A constraint must say what would BREACH it, which is the whole difference between a limit and a wish, and the column asks for the observable thing rather than the consequence. Aims are ranked because a client who wants five things equally wants nothing. Hardness is CAPPED by kind: only a safety constraint may veto, and not because it matters most but because it is the only one that is not the client's to trade - vetoing a course on their behalf takes their decision away and calls it protection. Duties to the court are deliberately absent from this vocabulary; they are duty.Breach. Every aim and constraint carries the words from the account it rests on, checked against the account, so an invented limit is discarded. LIVE, both directions: a bare brief yields none; a brief full of real limits yields four, correctly graded, none invented. | H15: The brief reaches the answer through the POSITION, with the trade-off requirement stated there - but nothing yet CHECKS that a given recommendation named its aim or its trade-off, so 'every recommendation traces to a ranked objective' is instructed rather than verified. Tradeoff exists as a type and no served stage produces one; until it does, an authorised trade-off (AB-20's DecisionRecord) has nothing to attach to. | I15: Add ClientObjectives and Constraints with priority, owner, source and review trigger. Require each strategy recommendation to state the objective served and any constraint breached or traded off. | J15: P1 | K15: Every recommendation traces to a ranked objective and either satisfies each material constraint or makes the trade-off explicit for decision. | L15: NM model + human/client priorities | M15: ABA Rule 2.1; BSB client research; PRD D16.8
A16: AB-09 | B16: Parties and posture | C16: D16.9 | D16: Not implemented | E16: Weak | F16: Role, side, posture, conflicts, thread identity, aliases, decisive identifiers, merge proposals and cross-thread separation are first-class. Unknown posture blocks directive advice and later inference cannot silently flip a stated role. | G16: nm/core/matter.py; nm/app/intake.py::_role; test_phase3_matter.py; test_talking.py::test_an_unresolved_posture_blocks_every_recommendation | H16: The model is excellent for one advocate/one represented side, but does not fully represent multi-party capacity, beneficial interests, aligned versus adverse parties, authorised representatives, multiple proceedings, orders or conflict relationships. Served state remains one thread. | I16: Extend Party and Proceeding models without weakening the existing posture gate. Add capacity, representation, interests, relationship edges and per-proceeding stage/order state; verify a multi-party live matter. | J16: P1 | K16: A multi-party, multi-proceeding matter preserves each identity and capacity, refuses ambiguous posture and never merges on labels alone. | L16: NM core behaviour | M16: PRD D8, D10A, D16.9
A17: AB-10 | B17: Fact model | C17: D16.10 | D17: Not implemented | E17: Weak | F17: Facts carry source, certainty, confirmation and thread; conflicting sources are both retained; chronology is ordered and source-carrying; corrections cascade through dependencies and report changed conclusions. | G17: nm/core/facts.py; nm/core/analysis.py::Chronology; nm/core/cascade.py; nm/core/provenance.py; test_phase3_matter.py; test_phase3_analysis.py; test_phase6_enterprise.py | H17: Privilege, sensitivity, hearsay/direct-knowledge basis and dispute status are not all represented on Fact. The served conversation persists role, cause, date and limitation but does not yet persist the full fact graph across turns. | I17: Enrich Fact with knowledge basis, dispute/privilege/sensitivity labels and evidence links. Persist and serve the real fact graph, then run correction and provenance assertions on a multi-turn live consultation. | J17: P1 | K17: Every material served statement walks back to a persisted proposition and source; conflicts survive; a material correction changes all and only its dependants. | L17: NM core behaviour | M17: PRD D9, D10, D16.10
A18: AB-11 | B18: Evidence and preservation | C18: D16.11 | D18: Not implemented | E18: Weak | F18: ProofPosition separates existence, admissibility, burden and standard; material requests name what they unblock; document facts retain provenance; retrieval findings carry locators, passages and verification state. | G18: nm/core/analysis.py::EvidenceItem, ProofPosition, MaterialRequest; nm/core/intake.py; nm/core/provenance.py; nm/evidence/*; test_phase3_analysis.py; test_phase2_evidence.py | H18: The implementation is proof-analysis and retrieval, not evidence preservation. There is no legal hold, original/copy distinction, metadata preservation, authenticity, chain of custody, spoliation warning, collection log or witness-contact protection. | I18: Add EvidenceItem custody and authenticity fields, PreservationPlan, CollectionEvent and hold/release workflow. Generate specific preservation actions during emergency triage and keep acquisition lawful and auditable. | J18: P1 | K18: Material evidence has holder, original/copy, authenticity basis, metadata/custody state and preservation action; an unpreserved at-risk item leads as an emergency. | L18: NM record + human custody actions | M18: BCI duties; BSB Professional Statement; PRD D16.11
... A35: AB-28 | B35: After each event and at closure | C35: D16.28 | D35: Not implemented | E35: Weak | F35: Gap close accounts for all remaining gaps; summaries and history preserve current state; matter export is scoped and provenance-aware; retention and erasure plans enumerate stores and derived data and refuse unexamined coverage. | G35: nm/core/queue.py::close_on_gaps; nm/core/summary.py; nm/core/audit.py; nm/edge/export.py; nm/core/retention.py; test_phase4_queue.py; test_phase6_enterprise.py | H35: There is no attendance note or event outcome/order/reasons/undertakings capture, appeal/enforcement/compliance decision, closure letter, client-money/original-document account, billing close, continuing-obligation checklist or lessons workflow. | I35: Add EventOutcome and FileClosure with required action/deadline accounting, appeal/enforcement decision, assets/funds/originals, approvals, export, ongoing duties and retention. Keep lessons de-identified and separate from client content. | J35: P1 | K35: An event cannot close without outcome and next actions; a matter cannot close with an unexplained deadline, client fund, asset, original document or retention obligation. | L35: Human closure + NM accounting | M35: BCI Rules; BSB client research; PRD D16.28
